clkUnit/diviseurClk.vhd
library IEEE;
use IEEE.std_logic_1164.all;

entity diviseurClk is
  generic(facteur : natural);
  port (
    clk, reset : in  std_logic;
    nclk       : out std_logic);
end diviseurClk;

architecture arch_divClk of diviseurClk is

  signal top : std_logic := '0';
  
begin  

  div : process (clk, reset)
    variable cpt : integer range 0 to facteur-1 := 0;
  begin 
    if reset = '0' then
      nclk <= '0';
      cpt := 0;
    elsif rising_edge(clk) then
      if(cpt = facteur - 1) then
        cpt := 0;
      else
        cpt := cpt + 1;
      end if;
      if cpt = 0 then
        nclk <= '1';
      else
        nclk <= '0';
      end if;
    end if;
  end process;

end arch_divClk;

clkUnit/clkUnit.vhd
library IEEE;
use IEEE.std_logic_1164.all;

entity clkUnit is
  
 port (
   clk, reset : in  std_logic;
   enableTX   : out std_logic;
   enableRX   : out std_logic);
    
end clkUnit;

architecture behavorial of clkUnit is

  component diviseurClk is
    generic (facteur : natural);
    port (
      clk, reset : in  std_logic;
      nclk       : out std_logic);
  end component diviseurClk;

begin

  inst_div_clk: diviseurClk
    generic map(16)
    port map(
      clk=>clk, 
      reset=>reset, 
      nclk=>enableTX
      );
  enableRX<=clk;

end behavorial;

TxUnit/TxUnit.vhd
library IEEE;
use IEEE.std_logic_1164.all;

entity TxUnit is
  port (
    clk, reset : in std_logic;
    enable : in std_logic; --cette entree rythme l'emission  
    ld : in std_logic;
    txd : out std_logic; --initialement a 1 (haut)
    regE : out std_logic; --etat des registres (E pour Enable) : 1 pour vide, 0 pour plein
    bufE : out std_logic; --etat des buffers
    data : in std_logic_vector(7 downto 0));
end TxUnit;

architecture behavorial of TxUnit is

  signal T : std_logic; --Transimission

  type t_etat is (IDLE, CHARGEMENT, PRE_EMISSION, EMISSION, LAST);
  signal etat : t_etat;

begin

  process(clk, reset)

    variable bufferT : std_logic_vector(7 downto 0); -- buffer register
    variable registerT : std_logic_vector(7 downto 0); --registre d'emission
    variable cpt : integer := 0;
    variable buff : std_logic; 
  begin
    if (reset = '0') then
      txd <= '1';
      regE <= '1';
      buff := '1';
      cpt := 0;
      etat <= IDLE;
    elsif rising_edge(clk) then
      case etat is
        when IDLE =>
          if (ld = '1') then
            bufferT := data;
            buff := '0';

            etat <= CHARGEMENT;

          end if;
        when CHARGEMENT => 
          registerT := bufferT;
          regE <= '0';
          buff := '1';
          etat <= EMISSION;

        when PRE_EMISSION =>
          if (ld='1' and buff='1') then
            bufferT := data;
            buff := '0';
          end if;
          if (enable = '1') then
            txd <= '0';
            cpt := 7;
            etat <= EMISSION;
          end if;

        when EMISSION =>
          if (ld='1' and buff='1') then
            bufferT := data;
            buff := '0';
          end if;
          if (enable = '1' and cpt > 0) then
            txd <= registerT(cpt);
            cpt := cpt - 1;
          elsif enable = '1' and cpt = 0 then
            txd <= registerT(cpt); --partie a ajouter
            etat <= LAST;
          end if;

        when LAST =>
          if (ld='1' and buff='1') then
            bufferT := data;
            buff := '0';
          end if;
          if (enable = '1' and buff='0') then
            etat <= CHARGEMENT;
          elsif (enable = '1' and buff='1') then
            txd <= '1';
            etat <= IDLE;
          end if;

        end case;
    end if;
    bufE <= buff;
  end process ;

end behavorial;

TxUnit/testTxUnit.vhd
--------------------------------------------------------------------------------
-- Company: 
-- Engineer:
--
-- Create Date:   12:09:49 10/31/2018
-- Design Name:   
-- Module Name:   testTxUnit.vhd
-- Project Name:  uart
-- Target Device:  
-- Tool versions:  
-- Description:   
-- 
-- VHDL Test Bench Created by ISE for module: TxUnit
-- 
-- Dependencies:
-- 
-- Revision:
-- Revision 0.01 - File Created
-- Additional Comments:
--
-- Notes: 
-- This testbench has been automatically generated using types std_logic and
-- std_logic_vector for the ports of the unit under test.  Xilinx recommends
-- that these types always be used for the top-level I/O of a design in order
-- to guarantee that the testbench will bind correctly to the post-implementation 
-- simulation model.
--------------------------------------------------------------------------------
LIBRARY ieee;
USE ieee.std_logic_1164.ALL;
 
-- Uncomment the following library declaration if using
-- arithmetic functions with Signed or Unsigned values
--USE ieee.numeric_std.ALL;
 
ENTITY testTxUnit IS
END testTxUnit;
 
ARCHITECTURE behavior OF testTxUnit IS 
 
    -- Component Declaration for the Unit Under Test (UUT)
 
    COMPONENT TxUnit
    PORT(
         clk : IN  std_logic;
         reset : IN  std_logic;
         enable : IN  std_logic;
         ld : IN  std_logic;
         txd : OUT  std_logic;
         regE : OUT  std_logic;
         bufE : OUT  std_logic;
         data : IN  std_logic_vector(7 downto 0)
        );
    END COMPONENT;
   
    COMPONENT clkUnit
    PORT(
         clk : IN  std_logic;
         reset : IN  std_logic;
         enableTX : OUT  std_logic;
         enableRX : OUT  std_logic
        );
    END COMPONENT;	

   signal clk : std_logic := '0';
   signal reset : std_logic := '0';
   signal enableTx : std_logic;
   signal enableRx : std_logic;
   signal ld : std_logic := '0';
   signal data : std_logic_vector(7 downto 0) := (others => '0');

   signal txd : std_logic;
   signal regE : std_logic;
   signal bufE : std_logic;

   -- Clock period definitions
   constant clk_period : time := 10 ns;
 
BEGIN
 
	-- Instantiate the Unit Under Test
   uut0: TxUnit PORT MAP (
          clk => clk,
          reset => reset,
          enable => enableTX,
          ld => ld,
          txd => txd,
          regE => regE,
          bufE => bufE,
          data => data
        );

   -- Instantiate the clkUnit
   clkUnit1: clkUnit PORT MAP (
          clk => clk,
          reset => reset,
          enableTX => enableTX,
          enableRX => enableRX
        );
		  
   -- Clock process definitions
   clk_process :process
   begin
     clk <= '0';
     wait for clk_period/2;
     clk <= '1';
     wait for clk_period/2;
   end process;
 
 
   -- Stimulus process
   stim_proc: process
   begin		
     -- maintien du reset durant 100 ns.
     wait for 100 ns;	
     reset <= '1';

     wait for 200 ns;

     -- l'émetteur est dispo ?
     if not (regE='1' and bufE='1') then
       wait until regE='1' and bufE='1';
     end if;

     -- si oui, on charge la donnée
     wait for clk_period;
     -- émission du caractère 0x55
     data <= "01010101";
     ld <= '1';

     -- on attend de voir que l'ordre d'émission
     -- a été bien pris en compte avant de rabaisser
     -- le signal ld
     if not (regE='1' and bufE='0') then
       wait until regE='1' and bufE='0';
     end if;
     wait for clk_period;
     ld <= '0';
	 
     -- compléter avec des tests qui montrent que la prise
     -- en compte de la demande d'émission d'un second
     -- caractère se fait lorsqu'on émet un premier caractère
     -- et ceci quelque soit l'étape d'émission
		
	  wait for 2300 ns;
	  -- émission du caractère 0x2A
     data <= "00101010";
     ld <= '1';

     -- on attend de voir que l'ordre d'émission
     -- a été bien pris en compte avant de rabaisser
     -- le signal ld
     if not (regE='1' and bufE='0') then
       wait until regE='1' and bufE='0';
     end if;
     wait for clk_period;
     ld <= '0';
	  
	  
	  wait for 2300 ns;
	  -- émission du caractère 0x42
     data <= "01000010";
     ld <= '1';

     -- on attend de voir que l'ordre d'émission
     -- a été bien pris en compte avant de rabaisser
     -- le signal ld
     if not (regE='1' and bufE='0') then
       wait until regE='1' and bufE='0';
     end if;
     wait for clk_period;
     ld <= '0';

     wait;
   end process;

END;

TxUnit/output.vcd
$date
   Tue Dec 10 10:54:30 2024
$end
$version
  P.20131013
$end
$timescale
  1ps
$end
$scope module testtxunit $end
$var wire 1 B clk $end
$var wire 1 C reset $end
$var wire 1 D enabletx $end
$var wire 1 E enablerx $end
$var wire 1 4 ld $end
$var wire 1 ? data [7] $end
$var wire 1 > data [6] $end
$var wire 1 = data [5] $end
$var wire 1 < data [4] $end
$var wire 1 ; data [3] $end
$var wire 1 : data [2] $end
$var wire 1 9 data [1] $end
$var wire 1 8 data [0] $end
$var wire 1 5 txd $end
$var wire 1 6 rege $end
$var wire 1 7 bufe $end
$scope module uut0 $end
$var wire 1 B clk $end
$var wire 1 C reset $end
$var wire 1 D enable $end
$var wire 1 4 ld $end
$var wire 1 5 txd $end
$var wire 1 6 rege $end
$var wire 1 7 bufe $end
$var wire 1 ? data [7] $end
$var wire 1 > data [6] $end
$var wire 1 = data [5] $end
$var wire 1 < data [4] $end
$var wire 1 ; data [3] $end
$var wire 1 : data [2] $end
$var wire 1 9 data [1] $end
$var wire 1 8 data [0] $end
$var wire 1 @ t $end
$upscope $end
$scope module clkUnit1 $end
$var wire 1 B clk $end
$var wire 1 C reset $end
$var wire 1 D enabletx $end
$var wire 1 E enablerx $end
$upscope $end
$upscope $end
$enddefinitions $end
#0
$dumpvars
0C
0B
xD
0E
04
0?
0>
0=
0<
0;
0:
09
08
15
16
17
x@
$end
#5000
1B
1E
#10000
0B
0E
#15000
1B
1E
#20000
0B
0E
#25000
1B
1E
#30000
0B
0E
#35000
1B
1E
#40000
0B
0E
#45000
1B
1E
#50000
0B
0E
#55000
1B
1E
#60000
0B
0E
#65000
1B
1E
#70000
0B
0E
#75000
1B
1E
#80000
0B
0E
#85000
1B
1E
#90000
0B
0E
#95000
1B
1E
#100000
1C
0B
0E
#105000
1B
1E
#110000
0B
0E
#115000
1B
1E
#120000
0B
0E
#125000
1B
1E
#130000
0B
0E
#135000
1B
1E
#140000
0B
0E
#145000
1B
1E
#150000
0B
0E
#155000
1B
1E
#160000
0B
0E
#165000
1B
1E
#170000
0B
0E
#175000
1B
1E
#180000
0B
0E
#185000
1B
1E
#190000
0B
0E
#195000
1B
1E
#200000
0B
0E
#205000
1B
1E
#210000
0B
0E
#215000
1B
1E
#220000
0B
0E
#225000
1B
1E
#230000
0B
0E
#235000
1B
1E
#240000
0B
0E
#245000
1B
1E
#250000
0B
0E
#255000
1B
1E
#260000
0B
0E
#265000
1B
1E
#270000
0B
0E
#275000
1B
1E
#280000
0B
0E
#285000
1B
1E
#290000
0B
0E
#295000
1B
1E
#300000
0B
0E
#305000
1B
1E
#310000
0B
0E
14
1>
1<
1:
18
#315000
1B
1E
07
#320000
0B
0E
#325000
1B
1E
04
06
17
#330000
0B
0E
#335000
1B
1E
#340000
0B
0E
#345000
1B
1E
#350000
0B
0E
#355000
1B
1E
#360000
0B
0E
#365000
1B
1E
#370000
0B
0E
#375000
1B
1E
#380000
0B
0E
#385000
1B
1E
#390000
0B
0E
#395000
1B
1E
#400000
0B
0E
#405000
1B
1E
#410000
0B
0E
#415000
1B
1E
#420000
0B
0E
#425000
1B
1E
#430000
0B
0E
#435000
1B
1E
#440000
0B
0E
#445000
1B
1E
#450000
0B
0E
#455000
1B
1E
#460000
0B
0E
#465000
1B
1E
#470000
0B
0E
#475000
1B
1E
#480000
0B
0E
#485000
1B
1E
#490000
0B
0E
#495000
1B
1E
#500000
0B
0E
#505000
1B
1E
#510000
0B
0E
#515000
1B
1E
#520000
0B
0E
#525000
1B
1E
#530000
0B
0E
#535000
1B
1E
#540000
0B
0E
#545000
1B
1E
#550000
0B
0E
#555000
1B
1E
#560000
0B
0E
#565000
1B
1E
#570000
0B
0E
#575000
1B
1E
#580000
0B
0E
#585000
1B
1E
#590000
0B
0E
#595000
1B
1E
#600000
0B
0E
#605000
1B
1E
#610000
0B
0E
#615000
1B
1E
#620000
0B
0E
#625000
1B
1E
#630000
0B
0E
#635000
1B
1E
#640000
0B
0E
#645000
1B
1E
#650000
0B
0E
#655000
1B
1E
#660000
0B
0E
#665000
1B
1E
#670000
0B
0E
#675000
1B
1E
#680000
0B
0E
#685000
1B
1E
#690000
0B
0E
#695000
1B
1E
#700000
0B
0E
#705000
1B
1E
#710000
0B
0E
#715000
1B
1E
#720000
0B
0E
#725000
1B
1E
#730000
0B
0E
#735000
1B
1E
#740000
0B
0E
#745000
1B
1E
#750000
0B
0E
#755000
1B
1E
#760000
0B
0E
#765000
1B
1E
#770000
0B
0E
#775000
1B
1E
#780000
0B
0E
#785000
1B
1E
#790000
0B
0E
#795000
1B
1E
#800000
0B
0E
#805000
1B
1E
#810000
0B
0E
#815000
1B
1E
#820000
0B
0E
#825000
1B
1E
#830000
0B
0E
#835000
1B
1E
#840000
0B
0E
#845000
1B
1E
#850000
0B
0E
#855000
1B
1E
#860000
0B
0E
#865000
1B
1E
#870000
0B
0E
#875000
1B
1E
#880000
0B
0E
#885000
1B
1E
#890000
0B
0E
#895000
1B
1E
#900000
0B
0E
#905000
1B
1E
#910000
0B
0E
#915000
1B
1E
#920000
0B
0E
#925000
1B
1E
#930000
0B
0E
#935000
1B
1E
#940000
0B
0E
#945000
1B
1E
#950000
0B
0E
#955000
1B
1E
#960000
0B
0E
#965000
1B
1E
#970000
0B
0E
#975000
1B
1E
#980000
0B
0E
#985000
1B
1E
#990000
0B
0E
#995000
1B
1E
#1000000
0B
0E
#1005000
1B
1E
#1010000
0B
0E
#1015000
1B
1E
#1020000
0B
0E
#1025000
1B
1E
#1030000
0B
0E
#1035000
1B
1E
#1040000
0B
0E
#1045000
1B
1E
#1050000
0B
0E
#1055000
1B
1E
#1060000
0B
0E
#1065000
1B
1E
#1070000
0B
0E
#1075000
1B
1E
#1080000
0B
0E
#1085000
1B
1E
#1090000
0B
0E
#1095000
1B
1E
#1100000
0B
0E
#1105000
1B
1E
#1110000
0B
0E
#1115000
1B
1E
#1120000
0B
0E
#1125000
1B
1E
#1130000
0B
0E
#1135000
1B
1E
#1140000
0B
0E
#1145000
1B
1E
#1150000
0B
0E
#1155000
1B
1E
#1160000
0B
0E
#1165000
1B
1E
#1170000
0B
0E
#1175000
1B
1E
#1180000
0B
0E
#1185000
1B
1E
#1190000
0B
0E
#1195000
1B
1E
#1200000
0B
0E
#1205000
1B
1E
#1210000
0B
0E
#1215000
1B
1E
#1220000
0B
0E
#1225000
1B
1E
#1230000
0B
0E
#1235000
1B
1E
#1240000
0B
0E
#1245000
1B
1E
#1250000
0B
0E
#1255000
1B
1E
#1260000
0B
0E
#1265000
1B
1E
#1270000
0B
0E
#1275000
1B
1E
#1280000
0B
0E
#1285000
1B
1E
#1290000
0B
0E
#1295000
1B
1E
#1300000
0B
0E
#1305000
1B
1E
#1310000
0B
0E
#1315000
1B
1E
#1320000
0B
0E
#1325000
1B
1E
#1330000
0B
0E
#1335000
1B
1E
#1340000
0B
0E
#1345000
1B
1E
#1350000
0B
0E
#1355000
1B
1E
#1360000
0B
0E
#1365000
1B
1E
#1370000
0B
0E
#1375000
1B
1E
#1380000
0B
0E
#1385000
1B
1E
#1390000
0B
0E
#1395000
1B
1E
#1400000
0B
0E
#1405000
1B
1E
#1410000
0B
0E
#1415000
1B
1E
#1420000
0B
0E
#1425000
1B
1E
#1430000
0B
0E
#1435000
1B
1E
#1440000
0B
0E
#1445000
1B
1E
#1450000
0B
0E
#1455000
1B
1E
#1460000
0B
0E
#1465000
1B
1E
#1470000
0B
0E
#1475000
1B
1E
#1480000
0B
0E
#1485000
1B
1E
#1490000
0B
0E
#1495000
1B
1E
#1500000
0B
0E
#1505000
1B
1E
#1510000
0B
0E
#1515000
1B
1E
#1520000
0B
0E
#1525000
1B
1E
#1530000
0B
0E
#1535000
1B
1E
#1540000
0B
0E
#1545000
1B
1E
#1550000
0B
0E
#1555000
1B
1E
#1560000
0B
0E
#1565000
1B
1E
#1570000
0B
0E
#1575000
1B
1E
#1580000
0B
0E
#1585000
1B
1E
#1590000
0B
0E
#1595000
1B
1E
#1600000
0B
0E
#1605000
1B
1E
#1610000
0B
0E
#1615000
1B
1E
#1620000
0B
0E
#1625000
1B
1E
#1630000
0B
0E
#1635000
1B
1E
#1640000
0B
0E
#1645000
1B
1E
#1650000
0B
0E
#1655000
1B
1E
#1660000
0B
0E
#1665000
1B
1E
#1670000
0B
0E
#1675000
1B
1E
#1680000
0B
0E
#1685000
1B
1E
#1690000
0B
0E
#1695000
1B
1E
#1700000
0B
0E
#1705000
1B
1E
#1710000
0B
0E
#1715000
1B
1E
#1720000
0B
0E
#1725000
1B
1E
#1730000
0B
0E
#1735000
1B
1E
#1740000
0B
0E
#1745000
1B
1E
#1750000
0B
0E
#1755000
1B
1E
#1760000
0B
0E
#1765000
1B
1E
#1770000
0B
0E
#1775000
1B
1E
#1780000
0B
0E
#1785000
1B
1E
#1790000
0B
0E
#1795000
1B
1E
#1800000
0B
0E
#1805000
1B
1E
#1810000
0B
0E
#1815000
1B
1E
#1820000
0B
0E
#1825000
1B
1E
#1830000
0B
0E
#1835000
1B
1E
#1840000
0B
0E
#1845000
1B
1E
#1850000
0B
0E
#1855000
1B
1E
#1860000
0B
0E
#1865000
1B
1E
#1870000
0B
0E
#1875000
1B
1E
#1880000
0B
0E
#1885000
1B
1E
#1890000
0B
0E
#1895000
1B
1E
#1900000
0B
0E
#1905000
1B
1E
#1910000
0B
0E
#1915000
1B
1E
#1920000
0B
0E
#1925000
1B
1E
#1930000
0B
0E
#1935000
1B
1E
#1940000
0B
0E
#1945000
1B
1E
#1950000
0B
0E
#1955000
1B
1E
#1960000
0B
0E
#1965000
1B
1E
#1970000
0B
0E
#1975000
1B
1E
#1980000
0B
0E
#1985000
1B
1E
#1990000
0B
0E
#1995000
1B
1E
#2000000
0B
0E
#2005000
1B
1E
#2010000
0B
0E
#2015000
1B
1E
#2020000
0B
0E
#2025000
1B
1E
#2030000
0B
0E
#2035000
1B
1E
#2040000
0B
0E
#2045000
1B
1E
#2050000
0B
0E
#2055000
1B
1E
#2060000
0B
0E
#2065000
1B
1E
#2070000
0B
0E
#2075000
1B
1E
#2080000
0B
0E
#2085000
1B
1E
#2090000
0B
0E
#2095000
1B
1E
#2100000
0B
0E
#2105000
1B
1E
#2110000
0B
0E
#2115000
1B
1E
#2120000
0B
0E
#2125000
1B
1E
#2130000
0B
0E
#2135000
1B
1E
#2140000
0B
0E
#2145000
1B
1E
#2150000
0B
0E
#2155000
1B
1E
#2160000
0B
0E
#2165000
1B
1E
#2170000
0B
0E
#2175000
1B
1E
#2180000
0B
0E
#2185000
1B
1E
#2190000
0B
0E
#2195000
1B
1E
#2200000
0B
0E
#2205000
1B
1E
#2210000
0B
0E
#2215000
1B
1E
#2220000
0B
0E
#2225000
1B
1E
#2230000
0B
0E
#2235000
1B
1E
#2240000
0B
0E
#2245000
1B
1E
#2250000
0B
0E
#2255000
1B
1E
#2260000
0B
0E
#2265000
1B
1E
#2270000
0B
0E
#2275000
1B
1E
#2280000
0B
0E
#2285000
1B
1E
#2290000
0B
0E
#2295000
1B
1E
#2300000
0B
0E
#2305000
1B
1E
#2310000
0B
0E
#2315000
1B
1E
#2320000
0B
0E
#2325000
1B
1E
#2330000
0B
0E
#2335000
1B
1E
#2340000
0B
0E
#2345000
1B
1E
#2350000
0B
0E
#2355000
1B
1E
#2360000
0B
0E
#2365000
1B
1E
#2370000
0B
0E
#2375000
1B
1E
#2380000
0B
0E
#2385000
1B
1E
#2390000
0B
0E
#2395000
1B
1E
#2400000
0B
0E
#2405000
1B
1E
#2410000
0B
0E
#2415000
1B
1E
#2420000
0B
0E
#2425000
1B
1E
#2430000
0B
0E
#2435000
1B
1E
#2440000
0B
0E
#2445000
1B
1E
#2450000
0B
0E
#2455000
1B
1E
#2460000
0B
0E
#2465000
1B
1E
#2470000
0B
0E
#2475000
1B
1E
#2480000
0B
0E
#2485000
1B
1E
#2490000
0B
0E
#2495000
1B
1E
#2500000
0B
0E
#2505000
1B
1E
#2510000
0B
0E
#2515000
1B
1E
#2520000
0B
0E
#2525000
1B
1E
#2530000
0B
0E
#2535000
1B
1E
#2540000
0B
0E
#2545000
1B
1E
#2550000
0B
0E
#2555000
1B
1E
#2560000
0B
0E
#2565000
1B
1E
#2570000
0B
0E
#2575000
1B
1E
#2580000
0B
0E
#2585000
1B
1E
#2590000
0B
0E
#2595000
1B
1E
#2600000
0B
0E
#2605000
1B
1E
#2610000
0B
0E
#2615000
1B
1E
#2620000
0B
0E
#2625000
1B
1E
#2630000
0B
0E
#2635000
1B
1E
#2640000
0B
0E
#2645000
1B
1E
#2650000
0B
0E
#2655000
1B
1E
#2660000
0B
0E
#2665000
1B
1E
#2670000
0B
0E
#2675000
1B
1E
#2680000
0B
0E
#2685000
1B
1E
#2690000
0B
0E
#2695000
1B
1E
#2700000
0B
0E
#2705000
1B
1E
#2710000
0B
0E
#2715000
1B
1E
#2720000
0B
0E
#2725000
1B
1E
#2730000
0B
0E
#2735000
1B
1E
#2740000
0B
0E
#2745000
1B
1E
#2750000
0B
0E
#2755000
1B
1E
#2760000
0B
0E
#2765000
1B
1E
#2770000
0B
0E
#2775000
1B
1E
#2780000
0B
0E
#2785000
1B
1E
#2790000
0B
0E
#2795000
1B
1E
#2800000
0B
0E
#2805000
1B
1E
#2810000
0B
0E
#2815000
1B
1E
#2820000
0B
0E
#2825000
1B
1E
#2830000
0B
0E
#2835000
1B
1E
#2840000
0B
0E
#2845000
1B
1E
#2850000
0B
0E
#2855000
1B
1E
#2860000
0B
0E
#2865000
1B
1E
#2870000
0B
0E
#2875000
1B
1E
#2880000
0B
0E
#2885000
1B
1E
#2890000
0B
0E
#2895000
1B
1E
#2900000
0B
0E
#2905000
1B
1E
#2910000
0B
0E
#2915000
1B
1E
#2920000
0B
0E
#2925000
1B
1E
#2930000
0B
0E
#2935000
1B
1E
#2940000
0B
0E
#2945000
1B
1E
#2950000
0B
0E
#2955000
1B
1E
#2960000
0B
0E
#2965000
1B
1E
#2970000
0B
0E
#2975000
1B
1E
#2980000
0B
0E
#2985000
1B
1E
#2990000
0B
0E
#2995000
1B
1E
#3000000
0B
0E
#3005000
1B
1E
#3010000
0B
0E
#3015000
1B
1E
#3020000
0B
0E
#3025000
1B
1E
#3030000
0B
0E
#3035000
1B
1E
#3040000
0B
0E
#3045000
1B
1E
#3050000
0B
0E
#3055000
1B
1E
#3060000
0B
0E
#3065000
1B
1E
#3070000
0B
0E
#3075000
1B
1E
#3080000
0B
0E
#3085000
1B
1E
#3090000
0B
0E
#3095000
1B
1E
#3100000
0B
0E
#3105000
1B
1E
#3110000
0B
0E
#3115000
1B
1E
#3120000
0B
0E
#3125000
1B
1E
#3130000
0B
0E
#3135000
1B
1E
#3140000
0B
0E
#3145000
1B
1E
#3150000
0B
0E
#3155000
1B
1E
#3160000
0B
0E
#3165000
1B
1E
#3170000
0B
0E
#3175000
1B
1E
#3180000
0B
0E
#3185000
1B
1E
#3190000
0B
0E
#3195000
1B
1E
#3200000
0B
0E
#3205000
1B
1E
#3210000
0B
0E
#3215000
1B
1E
#3220000
0B
0E
#3225000
1B
1E
#3230000
0B
0E
#3235000
1B
1E
#3240000
0B
0E
#3245000
1B
1E
#3250000
0B
0E
#3255000
1B
1E
#3260000
0B
0E
#3265000
1B
1E
#3270000
0B
0E
#3275000
1B
1E
#3280000
0B
0E
#3285000
1B
1E
#3290000
0B
0E
#3295000
1B
1E
#3300000
0B
0E
#3305000
1B
1E
#3310000
0B
0E
#3315000
1B
1E
#3320000
0B
0E
#3325000
1B
1E
#3330000
0B
0E
#3335000
1B
1E
#3340000
0B
0E
#3345000
1B
1E
#3350000
0B
0E
#3355000
1B
1E
#3360000
0B
0E
#3365000
1B
1E
#3370000
0B
0E
#3375000
1B
1E
#3380000
0B
0E
#3385000
1B
1E
#3390000
0B
0E
#3395000
1B
1E
#3400000
0B
0E
#3405000
1B
1E
#3410000
0B
0E
#3415000
1B
1E
#3420000
0B
0E
#3425000
1B
1E
#3430000
0B
0E
#3435000
1B
1E
#3440000
0B
0E
#3445000
1B
1E
#3450000
0B
0E
#3455000
1B
1E
#3460000
0B
0E
#3465000
1B
1E
#3470000
0B
0E
#3475000
1B
1E
#3480000
0B
0E
#3485000
1B
1E
#3490000
0B
0E
#3495000
1B
1E
#3500000
0B
0E
#3505000
1B
1E
#3510000
0B
0E
#3515000
1B
1E
#3520000
0B
0E
#3525000
1B
1E
#3530000
0B
0E
#3535000
1B
1E
#3540000
0B
0E
#3545000
1B
1E
#3550000
0B
0E
#3555000
1B
1E
#3560000
0B
0E
#3565000
1B
1E
#3570000
0B
0E
#3575000
1B
1E
#3580000
0B
0E
#3585000
1B
1E
#3590000
0B
0E
#3595000
1B
1E
#3600000
0B
0E
#3605000
1B
1E
#3610000
0B
0E
#3615000
1B
1E
#3620000
0B
0E
#3625000
1B
1E
#3630000
0B
0E
#3635000
1B
1E
#3640000
0B
0E
#3645000
1B
1E
#3650000
0B
0E
#3655000
1B
1E
#3660000
0B
0E
#3665000
1B
1E
#3670000
0B
0E
#3675000
1B
1E
#3680000
0B
0E
#3685000
1B
1E
#3690000
0B
0E
#3695000
1B
1E
#3700000
0B
0E
#3705000
1B
1E
#3710000
0B
0E
#3715000
1B
1E
#3720000
0B
0E
#3725000
1B
1E
#3730000
0B
0E
#3735000
1B
1E
#3740000
0B
0E
#3745000
1B
1E
#3750000
0B
0E
#3755000
1B
1E
#3760000
0B
0E
#3765000
1B
1E
#3770000
0B
0E
#3775000
1B
1E
#3780000
0B
0E
#3785000
1B
1E
#3790000
0B
0E
#3795000
1B
1E
#3800000
0B
0E
#3805000
1B
1E
#3810000
0B
0E
#3815000
1B
1E
#3820000
0B
0E
#3825000
1B
1E
#3830000
0B
0E
#3835000
1B
1E
#3840000
0B
0E
#3845000
1B
1E
#3850000
0B
0E
#3855000
1B
1E
#3860000
0B
0E
#3865000
1B
1E
#3870000
0B
0E
#3875000
1B
1E
#3880000
0B
0E
#3885000
1B
1E
#3890000
0B
0E
#3895000
1B
1E
#3900000
0B
0E
#3905000
1B
1E
#3910000
0B
0E
#3915000
1B
1E
#3920000
0B
0E
#3925000
1B
1E
#3930000
0B
0E
#3935000
1B
1E
#3940000
0B
0E
#3945000
1B
1E
#3950000
0B
0E
#3955000
1B
1E
#3960000
0B
0E
#3965000
1B
1E
#3970000
0B
0E
#3975000
1B
1E
#3980000
0B
0E
#3985000
1B
1E
#3990000
0B
0E
#3995000
1B
1E
#4000000
0B
0E
