clkUnit/diviseurClk.vhd
library IEEE;
use IEEE.std_logic_1164.all;

entity diviseurClk is
  generic(facteur : natural);
  port (
    clk, reset : in  std_logic;
    nclk       : out std_logic);
end diviseurClk;

architecture arch_divClk of diviseurClk is

  signal top : std_logic := '0';
  
begin  

  div : process (clk, reset)
    variable cpt : integer range 0 to facteur-1 := 0;
  begin 
    if reset = '0' then
      nclk <= '0';
      cpt := 0;
    elsif rising_edge(clk) then
      if(cpt = facteur - 1) then
        cpt := 0;
      else
        cpt := cpt + 1;
      end if;
      if cpt = 0 then
        nclk <= '1';
      else
        nclk <= '0';
      end if;
    end if;
  end process;

end arch_divClk;

clkUnit/clkUnit.vhd
library IEEE;
use IEEE.std_logic_1164.all;

entity clkUnit is
  
 port (
   clk, reset : in  std_logic;
   enableTX   : out std_logic;
   enableRX   : out std_logic);
    
end clkUnit;

architecture behavorial of clkUnit is

  component diviseurClk is
    generic (facteur : natural);
    port (
      clk, reset : in  std_logic;
      nclk       : out std_logic);
  end component diviseurClk;

begin

  inst_div_clk: diviseurClk
    generic map(16)
    port map(
      clk=>clk, 
      reset=>reset, 
      nclk=>enableTX
      );
  enableRX<=clk;

end behavorial;

TxUnit/TxUnit.vhd
library IEEE;
use IEEE.std_logic_1164.all;

entity TxUnit is
  port (
    clk, reset : in std_logic;
    enable : in std_logic; --cette entree rythme l'emission  
    ld : in std_logic;
    txd : out std_logic; --initialement a 1 (haut)
    regE : out std_logic; --etat des registres (E pour Enable) : 1 pour vide, 0 pour plein
    bufE : out std_logic; --etat des buffers
    data : in std_logic_vector(7 downto 0));
end TxUnit;

architecture behavorial of TxUnit is

  signal T : std_logic; --Transimission
  signal bit_parite : std_logic;

  type t_etat is (IDLE, CHARGEMENT, PRE_EMISSION, EMISSION, EMISSION_PARITE, LAST);
  signal etat : t_etat;
  

begin

  process(clk, reset)

    variable bufferT : std_logic_vector(7 downto 0); -- buffer register
    variable registerT : std_logic_vector(7 downto 0); --registre d'emission
    variable cpt : integer := 0;
    variable buff : std_logic := '1'; 
  begin
    if (reset = '0') then
      txd <= '1';
      regE <= '1';
      buff := '1';
      cpt := 0;
		bufferT := (others => '0');
		registerT := (others => '0');
		bit_parite <= '0';
      etat <= IDLE;
    elsif rising_edge(clk) then
      case etat is
        when IDLE =>
          if (ld = '1') then
            bufferT := data;
            buff := '0';
            etat <= CHARGEMENT;
          end if;
        when CHARGEMENT =>
          bit_parite <= '0';
          registerT := bufferT;
          regE <= '0';
          buff := '1';
          etat <= PRE_EMISSION;

        when PRE_EMISSION =>
          if (ld='1' and buff='1') then
            bufferT := data;
            buff := '0';
          end if;
          if (enable = '1') then
            txd <= '0';
            cpt := 7;
            etat <= EMISSION;
          end if;

        when EMISSION =>
          if (ld='1' and buff='1') then
            bufferT := data;
            buff := '0';
          end if;
          if (enable = '1' and cpt > 0) then
            txd <= registerT(cpt);
				bit_parite <= bit_parite xor registerT(cpt);
            cpt := cpt - 1;
          elsif enable = '1' and cpt = 0 then
            txd <= registerT(cpt);
				bit_parite <= bit_parite xor registerT(cpt);
            etat <= EMISSION_PARITE;
          end if;
		
		 when EMISSION_PARITE => 
			 if (enable = '1') then
				registerT := (others => '0');
				regE <= '1';
				txd <= bit_parite;
				etat <= LAST;
      end if;
      if (ld='1' and buff='1') then
        bufferT := data;
        buff := '0';
      end if;
			

      when LAST =>
        if (ld='1' and buff='1') then
          bufferT := data;
          buff := '0';
        end if;

        if (enable = '1') then
          txd <= '1';
          if (buff='0') then
            etat <= CHARGEMENT;
          else
            etat <= IDLE;
          end if;
        end if;
      end case;
    end if;
    bufE <= buff;
  end process ;

end behavorial;

TxUnit/testTxUnit.vhd
--------------------------------------------------------------------------------
-- Company: 
-- Engineer:
--
-- Create Date:   12:09:49 10/31/2018
-- Design Name:   
-- Module Name:   testTxUnit.vhd
-- Project Name:  uart
-- Target Device:  
-- Tool versions:  
-- Description:   
-- 
-- VHDL Test Bench Created by ISE for module: TxUnit
-- 
-- Dependencies:
-- 
-- Revision:
-- Revision 0.01 - File Created
-- Additional Comments:
--
-- Notes: 
-- This testbench has been automatically generated using types std_logic and
-- std_logic_vector for the ports of the unit under test.  Xilinx recommends
-- that these types always be used for the top-level I/O of a design in order
-- to guarantee that the testbench will bind correctly to the post-implementation 
-- simulation model.
--------------------------------------------------------------------------------
LIBRARY ieee;
USE ieee.std_logic_1164.ALL;
 
-- Uncomment the following library declaration if using
-- arithmetic functions with Signed or Unsigned values
--USE ieee.numeric_std.ALL;
 
ENTITY testTxUnit IS
END testTxUnit;
 
ARCHITECTURE behavior OF testTxUnit IS 
 
    -- Component Declaration for the Unit Under Test (UUT)
 
    COMPONENT TxUnit
    PORT(
         clk : IN  std_logic;
         reset : IN  std_logic;
         enable : IN  std_logic;
         ld : IN  std_logic;
         txd : OUT  std_logic;
         regE : OUT  std_logic;
         bufE : OUT  std_logic;
         data : IN  std_logic_vector(7 downto 0)
        );
    END COMPONENT;
   
    COMPONENT clkUnit
    PORT(
         clk : IN  std_logic;
         reset : IN  std_logic;
         enableTX : OUT  std_logic;
         enableRX : OUT  std_logic
        );
    END COMPONENT;	

   signal clk : std_logic := '0';
   signal reset : std_logic := '0';
   signal enableTx : std_logic;
   signal enableRx : std_logic;
   signal ld : std_logic := '0';
   signal data : std_logic_vector(7 downto 0) := (others => '0');

   signal txd : std_logic;
   signal regE : std_logic;
   signal bufE : std_logic;

   -- Clock period definitions
   constant clk_period : time := 10 ns;
 
BEGIN
 
	-- Instantiate the Unit Under Test
   uut0: TxUnit PORT MAP (
          clk => clk,
          reset => reset,
          enable => enableTX,
          ld => ld,
          txd => txd,
          regE => regE,
          bufE => bufE,
          data => data
        );

   -- Instantiate the clkUnit
   clkUnit1: clkUnit PORT MAP (
          clk => clk,
          reset => reset,
          enableTX => enableTX,
          enableRX => enableRX
        );
		  
   -- Clock process definitions
   clk_process :process
   begin
     clk <= '0';
     wait for clk_period/2;
     clk <= '1';
     wait for clk_period/2;
   end process;
 
 
   -- Stimulus process
   stim_proc: process
   begin		
     -- maintien du reset durant 100 ns.
     wait for 100 ns;	
     reset <= '1';

     wait for 200 ns;

     -- l'émetteur est dispo ?
     if not (regE='1' and bufE='1') then
       wait until regE='1' and bufE='1';
     end if;

     -- si oui, on charge la donnée
     wait for clk_period;
     -- émission du caractère 0x55
     data <= "01010101";
     ld <= '1';

     -- on attend de voir que l'ordre d'émission
     -- a été bien pris en compte avant de rabaisser
     -- le signal ld
     if not (regE='1' and bufE='0') then
       wait until regE='1' and bufE='0';
     end if;
     wait for clk_period;
     ld <= '0';
	 
     -- compléter avec des tests qui montrent que la prise
     -- en compte de la demande d'émission d'un second
     -- caractère se fait lorsqu'on émet un premier caractère
     -- et ceci quelque soit l'étape d'émission
		
	  wait for 2300 ns;
	  -- émission du caractère 0x2A
     data <= "00101010";
     ld <= '1';

     -- on attend de voir que l'ordre d'émission
     -- a été bien pris en compte avant de rabaisser
     -- le signal ld
     if not (regE='1' and bufE='0') then
       wait until regE='1' and bufE='0';
     end if;
     wait for clk_period;
     ld <= '0';
	  
	  
	  wait for 2300 ns;
	  -- émission du caractère 0x42
     data <= "01000010";
     ld <= '1';

     -- on attend de voir que l'ordre d'émission
     -- a été bien pris en compte avant de rabaisser
     -- le signal ld
     if not (regE='1' and bufE='0') then
       wait until regE='1' and bufE='0';
     end if;
     wait for clk_period;
     ld <= '0';

     wait;
   end process;

END;

TxUnit/output.vcd
$date
   Tue Jan  7 08:47:03 2025
$end
$version
  P.20131013
$end
$timescale
  1ps
$end
$scope module testtxunit $end
$var wire 1 G clk $end
$var wire 1 H reset $end
$var wire 1 I enabletx $end
$var wire 1 F enablerx $end
$var wire 1 4 ld $end
$var wire 1 ? data [7] $end
$var wire 1 > data [6] $end
$var wire 1 = data [5] $end
$var wire 1 < data [4] $end
$var wire 1 ; data [3] $end
$var wire 1 : data [2] $end
$var wire 1 9 data [1] $end
$var wire 1 8 data [0] $end
$var wire 1 5 txd $end
$var wire 1 6 rege $end
$var wire 1 7 bufe $end
$scope module uut0 $end
$var wire 1 G clk $end
$var wire 1 H reset $end
$var wire 1 I enable $end
$var wire 1 4 ld $end
$var wire 1 5 txd $end
$var wire 1 6 rege $end
$var wire 1 7 bufe $end
$var wire 1 ? data [7] $end
$var wire 1 > data [6] $end
$var wire 1 = data [5] $end
$var wire 1 < data [4] $end
$var wire 1 ; data [3] $end
$var wire 1 : data [2] $end
$var wire 1 9 data [1] $end
$var wire 1 8 data [0] $end
$var wire 1 @ t $end
$var wire 1 A bit_parite $end
$upscope $end
$scope module clkUnit1 $end
$var wire 1 G clk $end
$var wire 1 H reset $end
$var wire 1 I enabletx $end
$var wire 1 F enablerx $end
$scope module inst_div_clk $end
$var wire 1 G clk $end
$var wire 1 H reset $end
$var wire 1 I nclk $end
$var wire 1 J top $end
$upscope $end
$upscope $end
$upscope $end
$enddefinitions $end
#0
$dumpvars
0H
0G
0I
0F
04
0?
0>
0=
0<
0;
0:
09
08
15
16
17
x@
0A
0J
$end
#5000
1G
1F
#10000
0G
0F
#15000
1G
1F
#20000
0G
0F
#25000
1G
1F
#30000
0G
0F
#35000
1G
1F
#40000
0G
0F
#45000
1G
1F
#50000
0G
0F
#55000
1G
1F
#60000
0G
0F
#65000
1G
1F
#70000
0G
0F
#75000
1G
1F
#80000
0G
0F
#85000
1G
1F
#90000
0G
0F
#95000
1G
1F
#100000
1H
0G
0F
#105000
1G
1F
#110000
0G
0F
#115000
1G
1F
#120000
0G
0F
#125000
1G
1F
#130000
0G
0F
#135000
1G
1F
#140000
0G
0F
#145000
1G
1F
#150000
0G
0F
#155000
1G
1F
#160000
0G
0F
#165000
1G
1F
#170000
0G
0F
#175000
1G
1F
#180000
0G
0F
#185000
1G
1F
#190000
0G
0F
#195000
1G
1F
#200000
0G
0F
#205000
1G
1F
#210000
0G
0F
#215000
1G
1F
#220000
0G
0F
#225000
1G
1F
#230000
0G
0F
#235000
1G
1F
#240000
0G
0F
#245000
1G
1F
#250000
0G
0F
#255000
1G
1I
1F
#260000
0G
0F
#265000
1G
0I
1F
#270000
0G
0F
#275000
1G
1F
#280000
0G
0F
#285000
1G
1F
#290000
0G
0F
#295000
1G
1F
#300000
0G
0F
#305000
1G
1F
#310000
0G
0F
14
1>
1<
1:
18
#315000
1G
1F
07
#320000
0G
0F
#325000
1G
1F
04
06
17
#330000
0G
0F
#335000
1G
1F
#340000
0G
0F
#345000
1G
1F
#350000
0G
0F
#355000
1G
1F
#360000
0G
0F
#365000
1G
1F
#370000
0G
0F
#375000
1G
1F
#380000
0G
0F
#385000
1G
1F
#390000
0G
0F
#395000
1G
1F
#400000
0G
0F
#405000
1G
1F
#410000
0G
0F
#415000
1G
1I
1F
#420000
0G
0F
#425000
1G
0I
1F
05
#430000
0G
0F
#435000
1G
1F
#440000
0G
0F
#445000
1G
1F
#450000
0G
0F
#455000
1G
1F
#460000
0G
0F
#465000
1G
1F
#470000
0G
0F
#475000
1G
1F
#480000
0G
0F
#485000
1G
1F
#490000
0G
0F
#495000
1G
1F
#500000
0G
0F
#505000
1G
1F
#510000
0G
0F
#515000
1G
1F
#520000
0G
0F
#525000
1G
1F
#530000
0G
0F
#535000
1G
1F
#540000
0G
0F
#545000
1G
1F
#550000
0G
0F
#555000
1G
1F
#560000
0G
0F
#565000
1G
1F
#570000
0G
0F
#575000
1G
1I
1F
#580000
0G
0F
#585000
1G
0I
1F
#590000
0G
0F
#595000
1G
1F
#600000
0G
0F
#605000
1G
1F
#610000
0G
0F
#615000
1G
1F
#620000
0G
0F
#625000
1G
1F
#630000
0G
0F
#635000
1G
1F
#640000
0G
0F
#645000
1G
1F
#650000
0G
0F
#655000
1G
1F
#660000
0G
0F
#665000
1G
1F
#670000
0G
0F
#675000
1G
1F
#680000
0G
0F
#685000
1G
1F
#690000
0G
0F
#695000
1G
1F
#700000
0G
0F
#705000
1G
1F
#710000
0G
0F
#715000
1G
1F
#720000
0G
0F
#725000
1G
1F
#730000
0G
0F
#735000
1G
1I
1F
#740000
0G
0F
#745000
1G
0I
1F
15
1A
#750000
0G
0F
#755000
1G
1F
#760000
0G
0F
#765000
1G
1F
#770000
0G
0F
#775000
1G
1F
#780000
0G
0F
#785000
1G
1F
#790000
0G
0F
#795000
1G
1F
#800000
0G
0F
#805000
1G
1F
#810000
0G
0F
#815000
1G
1F
#820000
0G
0F
#825000
1G
1F
#830000
0G
0F
#835000
1G
1F
#840000
0G
0F
#845000
1G
1F
#850000
0G
0F
#855000
1G
1F
#860000
0G
0F
#865000
1G
1F
#870000
0G
0F
#875000
1G
1F
#880000
0G
0F
#885000
1G
1F
#890000
0G
0F
#895000
1G
1I
1F
#900000
0G
0F
#905000
1G
0I
1F
05
#910000
0G
0F
#915000
1G
1F
#920000
0G
0F
#925000
1G
1F
#930000
0G
0F
#935000
1G
1F
#940000
0G
0F
#945000
1G
1F
#950000
0G
0F
#955000
1G
1F
#960000
0G
0F
#965000
1G
1F
#970000
0G
0F
#975000
1G
1F
#980000
0G
0F
#985000
1G
1F
#990000
0G
0F
#995000
1G
1F
#1000000
0G
0F
#1005000
1G
1F
#1010000
0G
0F
#1015000
1G
1F
#1020000
0G
0F
#1025000
1G
1F
#1030000
0G
0F
#1035000
1G
1F
#1040000
0G
0F
#1045000
1G
1F
#1050000
0G
0F
#1055000
1G
1I
1F
#1060000
0G
0F
#1065000
1G
0I
1F
15
0A
#1070000
0G
0F
#1075000
1G
1F
#1080000
0G
0F
#1085000
1G
1F
#1090000
0G
0F
#1095000
1G
1F
#1100000
0G
0F
#1105000
1G
1F
#1110000
0G
0F
#1115000
1G
1F
#1120000
0G
0F
#1125000
1G
1F
#1130000
0G
0F
#1135000
1G
1F
#1140000
0G
0F
#1145000
1G
1F
#1150000
0G
0F
#1155000
1G
1F
#1160000
0G
0F
#1165000
1G
1F
#1170000
0G
0F
#1175000
1G
1F
#1180000
0G
0F
#1185000
1G
1F
#1190000
0G
0F
#1195000
1G
1F
#1200000
0G
0F
#1205000
1G
1F
#1210000
0G
0F
#1215000
1G
1I
1F
#1220000
0G
0F
#1225000
1G
0I
1F
05
#1230000
0G
0F
#1235000
1G
1F
#1240000
0G
0F
#1245000
1G
1F
#1250000
0G
0F
#1255000
1G
1F
#1260000
0G
0F
#1265000
1G
1F
#1270000
0G
0F
#1275000
1G
1F
#1280000
0G
0F
#1285000
1G
1F
#1290000
0G
0F
#1295000
1G
1F
#1300000
0G
0F
#1305000
1G
1F
#1310000
0G
0F
#1315000
1G
1F
#1320000
0G
0F
#1325000
1G
1F
#1330000
0G
0F
#1335000
1G
1F
#1340000
0G
0F
#1345000
1G
1F
#1350000
0G
0F
#1355000
1G
1F
#1360000
0G
0F
#1365000
1G
1F
#1370000
0G
0F
#1375000
1G
1I
1F
#1380000
0G
0F
#1385000
1G
0I
1F
15
1A
#1390000
0G
0F
#1395000
1G
1F
#1400000
0G
0F
#1405000
1G
1F
#1410000
0G
0F
#1415000
1G
1F
#1420000
0G
0F
#1425000
1G
1F
#1430000
0G
0F
#1435000
1G
1F
#1440000
0G
0F
#1445000
1G
1F
#1450000
0G
0F
#1455000
1G
1F
#1460000
0G
0F
#1465000
1G
1F
#1470000
0G
0F
#1475000
1G
1F
#1480000
0G
0F
#1485000
1G
1F
#1490000
0G
0F
#1495000
1G
1F
#1500000
0G
0F
#1505000
1G
1F
#1510000
0G
0F
#1515000
1G
1F
#1520000
0G
0F
#1525000
1G
1F
#1530000
0G
0F
#1535000
1G
1I
1F
#1540000
0G
0F
#1545000
1G
0I
1F
05
#1550000
0G
0F
#1555000
1G
1F
#1560000
0G
0F
#1565000
1G
1F
#1570000
0G
0F
#1575000
1G
1F
#1580000
0G
0F
#1585000
1G
1F
#1590000
0G
0F
#1595000
1G
1F
#1600000
0G
0F
#1605000
1G
1F
#1610000
0G
0F
#1615000
1G
1F
#1620000
0G
0F
#1625000
1G
1F
#1630000
0G
0F
#1635000
1G
1F
#1640000
0G
0F
#1645000
1G
1F
#1650000
0G
0F
#1655000
1G
1F
#1660000
0G
0F
#1665000
1G
1F
#1670000
0G
0F
#1675000
1G
1F
#1680000
0G
0F
#1685000
1G
1F
#1690000
0G
0F
#1695000
1G
1I
1F
#1700000
0G
0F
#1705000
1G
0I
1F
15
0A
#1710000
0G
0F
#1715000
1G
1F
#1720000
0G
0F
#1725000
1G
1F
#1730000
0G
0F
#1735000
1G
1F
#1740000
0G
0F
#1745000
1G
1F
#1750000
0G
0F
#1755000
1G
1F
#1760000
0G
0F
#1765000
1G
1F
#1770000
0G
0F
#1775000
1G
1F
#1780000
0G
0F
#1785000
1G
1F
#1790000
0G
0F
#1795000
1G
1F
#1800000
0G
0F
#1805000
1G
1F
#1810000
0G
0F
#1815000
1G
1F
#1820000
0G
0F
#1825000
1G
1F
#1830000
0G
0F
#1835000
1G
1F
#1840000
0G
0F
#1845000
1G
1F
#1850000
0G
0F
#1855000
1G
1I
1F
#1860000
0G
0F
#1865000
1G
0I
1F
05
16
#1870000
0G
0F
#1875000
1G
1F
#1880000
0G
0F
#1885000
1G
1F
#1890000
0G
0F
#1895000
1G
1F
#1900000
0G
0F
#1905000
1G
1F
#1910000
0G
0F
#1915000
1G
1F
#1920000
0G
0F
#1925000
1G
1F
#1930000
0G
0F
#1935000
1G
1F
#1940000
0G
0F
#1945000
1G
1F
#1950000
0G
0F
#1955000
1G
1F
#1960000
0G
0F
#1965000
1G
1F
#1970000
0G
0F
#1975000
1G
1F
#1980000
0G
0F
#1985000
1G
1F
#1990000
0G
0F
#1995000
1G
1F
#2000000
0G
0F
#2005000
1G
1F
#2010000
0G
0F
#2015000
1G
1I
1F
#2020000
0G
0F
#2025000
1G
0I
1F
15
#2030000
0G
0F
#2035000
1G
1F
#2040000
0G
0F
#2045000
1G
1F
#2050000
0G
0F
#2055000
1G
1F
#2060000
0G
0F
#2065000
1G
1F
#2070000
0G
0F
#2075000
1G
1F
#2080000
0G
0F
#2085000
1G
1F
#2090000
0G
0F
#2095000
1G
1F
#2100000
0G
0F
#2105000
1G
1F
#2110000
0G
0F
#2115000
1G
1F
#2120000
0G
0F
#2125000
1G
1F
#2130000
0G
0F
#2135000
1G
1F
#2140000
0G
0F
#2145000
1G
1F
#2150000
0G
0F
#2155000
1G
1F
#2160000
0G
0F
#2165000
1G
1F
#2170000
0G
0F
#2175000
1G
1I
1F
#2180000
0G
0F
#2185000
1G
0I
1F
#2190000
0G
0F
#2195000
1G
1F
#2200000
0G
0F
#2205000
1G
1F
#2210000
0G
0F
#2215000
1G
1F
#2220000
0G
0F
#2225000
1G
1F
#2230000
0G
0F
#2235000
1G
1F
#2240000
0G
0F
#2245000
1G
1F
#2250000
0G
0F
#2255000
1G
1F
#2260000
0G
0F
#2265000
1G
1F
#2270000
0G
0F
#2275000
1G
1F
#2280000
0G
0F
#2285000
1G
1F
#2290000
0G
0F
#2295000
1G
1F
#2300000
0G
0F
#2305000
1G
1F
#2310000
0G
0F
#2315000
1G
1F
#2320000
0G
0F
#2325000
1G
1F
#2330000
0G
0F
#2335000
1G
1I
1F
#2340000
0G
0F
#2345000
1G
0I
1F
#2350000
0G
0F
#2355000
1G
1F
#2360000
0G
0F
#2365000
1G
1F
#2370000
0G
0F
#2375000
1G
1F
#2380000
0G
0F
#2385000
1G
1F
#2390000
0G
0F
#2395000
1G
1F
#2400000
0G
0F
#2405000
1G
1F
#2410000
0G
0F
#2415000
1G
1F
#2420000
0G
0F
#2425000
1G
1F
#2430000
0G
0F
#2435000
1G
1F
#2440000
0G
0F
#2445000
1G
1F
#2450000
0G
0F
#2455000
1G
1F
#2460000
0G
0F
#2465000
1G
1F
#2470000
0G
0F
#2475000
1G
1F
#2480000
0G
0F
#2485000
1G
1F
#2490000
0G
0F
#2495000
1G
1I
1F
#2500000
0G
0F
#2505000
1G
0I
1F
#2510000
0G
0F
#2515000
1G
1F
#2520000
0G
0F
#2525000
1G
1F
#2530000
0G
0F
#2535000
1G
1F
#2540000
0G
0F
#2545000
1G
1F
#2550000
0G
0F
#2555000
1G
1F
#2560000
0G
0F
#2565000
1G
1F
#2570000
0G
0F
#2575000
1G
1F
#2580000
0G
0F
#2585000
1G
1F
#2590000
0G
0F
#2595000
1G
1F
#2600000
0G
0F
#2605000
1G
1F
#2610000
0G
0F
#2615000
1G
1F
#2620000
0G
0F
#2625000
1G
1F
14
0>
1=
0<
1;
0:
19
08
07
#2630000
0G
0F
#2635000
1G
1F
04
06
17
#2640000
0G
0F
#2645000
1G
1F
#2650000
0G
0F
#2655000
1G
1I
1F
#2660000
0G
0F
#2665000
1G
0I
1F
05
#2670000
0G
0F
#2675000
1G
1F
#2680000
0G
0F
#2685000
1G
1F
#2690000
0G
0F
#2695000
1G
1F
#2700000
0G
0F
#2705000
1G
1F
#2710000
0G
0F
#2715000
1G
1F
#2720000
0G
0F
#2725000
1G
1F
#2730000
0G
0F
#2735000
1G
1F
#2740000
0G
0F
#2745000
1G
1F
#2750000
0G
0F
#2755000
1G
1F
#2760000
0G
0F
#2765000
1G
1F
#2770000
0G
0F
#2775000
1G
1F
#2780000
0G
0F
#2785000
1G
1F
#2790000
0G
0F
#2795000
1G
1F
#2800000
0G
0F
#2805000
1G
1F
#2810000
0G
0F
#2815000
1G
1I
1F
#2820000
0G
0F
#2825000
1G
0I
1F
#2830000
0G
0F
#2835000
1G
1F
#2840000
0G
0F
#2845000
1G
1F
#2850000
0G
0F
#2855000
1G
1F
#2860000
0G
0F
#2865000
1G
1F
#2870000
0G
0F
#2875000
1G
1F
#2880000
0G
0F
#2885000
1G
1F
#2890000
0G
0F
#2895000
1G
1F
#2900000
0G
0F
#2905000
1G
1F
#2910000
0G
0F
#2915000
1G
1F
#2920000
0G
0F
#2925000
1G
1F
#2930000
0G
0F
#2935000
1G
1F
#2940000
0G
0F
#2945000
1G
1F
#2950000
0G
0F
#2955000
1G
1F
#2960000
0G
0F
#2965000
1G
1F
#2970000
0G
0F
#2975000
1G
1I
1F
#2980000
0G
0F
#2985000
1G
0I
1F
#2990000
0G
0F
#2995000
1G
1F
#3000000
0G
0F
#3005000
1G
1F
#3010000
0G
0F
#3015000
1G
1F
#3020000
0G
0F
#3025000
1G
1F
#3030000
0G
0F
#3035000
1G
1F
#3040000
0G
0F
#3045000
1G
1F
#3050000
0G
0F
#3055000
1G
1F
#3060000
0G
0F
#3065000
1G
1F
#3070000
0G
0F
#3075000
1G
1F
#3080000
0G
0F
#3085000
1G
1F
#3090000
0G
0F
#3095000
1G
1F
#3100000
0G
0F
#3105000
1G
1F
#3110000
0G
0F
#3115000
1G
1F
#3120000
0G
0F
#3125000
1G
1F
#3130000
0G
0F
#3135000
1G
1I
1F
#3140000
0G
0F
#3145000
1G
0I
1F
15
1A
#3150000
0G
0F
#3155000
1G
1F
#3160000
0G
0F
#3165000
1G
1F
#3170000
0G
0F
#3175000
1G
1F
#3180000
0G
0F
#3185000
1G
1F
#3190000
0G
0F
#3195000
1G
1F
#3200000
0G
0F
#3205000
1G
1F
#3210000
0G
0F
#3215000
1G
1F
#3220000
0G
0F
#3225000
1G
1F
#3230000
0G
0F
#3235000
1G
1F
#3240000
0G
0F
#3245000
1G
1F
#3250000
0G
0F
#3255000
1G
1F
#3260000
0G
0F
#3265000
1G
1F
#3270000
0G
0F
#3275000
1G
1F
#3280000
0G
0F
#3285000
1G
1F
#3290000
0G
0F
#3295000
1G
1I
1F
#3300000
0G
0F
#3305000
1G
0I
1F
05
#3310000
0G
0F
#3315000
1G
1F
#3320000
0G
0F
#3325000
1G
1F
#3330000
0G
0F
#3335000
1G
1F
#3340000
0G
0F
#3345000
1G
1F
#3350000
0G
0F
#3355000
1G
1F
#3360000
0G
0F
#3365000
1G
1F
#3370000
0G
0F
#3375000
1G
1F
#3380000
0G
0F
#3385000
1G
1F
#3390000
0G
0F
#3395000
1G
1F
#3400000
0G
0F
#3405000
1G
1F
#3410000
0G
0F
#3415000
1G
1F
#3420000
0G
0F
#3425000
1G
1F
#3430000
0G
0F
#3435000
1G
1F
#3440000
0G
0F
#3445000
1G
1F
#3450000
0G
0F
#3455000
1G
1I
1F
#3460000
0G
0F
#3465000
1G
0I
1F
15
0A
#3470000
0G
0F
#3475000
1G
1F
#3480000
0G
0F
#3485000
1G
1F
#3490000
0G
0F
#3495000
1G
1F
#3500000
0G
0F
#3505000
1G
1F
#3510000
0G
0F
#3515000
1G
1F
#3520000
0G
0F
#3525000
1G
1F
#3530000
0G
0F
#3535000
1G
1F
#3540000
0G
0F
#3545000
1G
1F
#3550000
0G
0F
#3555000
1G
1F
#3560000
0G
0F
#3565000
1G
1F
#3570000
0G
0F
#3575000
1G
1F
#3580000
0G
0F
#3585000
1G
1F
#3590000
0G
0F
#3595000
1G
1F
#3600000
0G
0F
#3605000
1G
1F
#3610000
0G
0F
#3615000
1G
1I
1F
#3620000
0G
0F
#3625000
1G
0I
1F
05
#3630000
0G
0F
#3635000
1G
1F
#3640000
0G
0F
#3645000
1G
1F
#3650000
0G
0F
#3655000
1G
1F
#3660000
0G
0F
#3665000
1G
1F
#3670000
0G
0F
#3675000
1G
1F
#3680000
0G
0F
#3685000
1G
1F
#3690000
0G
0F
#3695000
1G
1F
#3700000
0G
0F
#3705000
1G
1F
#3710000
0G
0F
#3715000
1G
1F
#3720000
0G
0F
#3725000
1G
1F
#3730000
0G
0F
#3735000
1G
1F
#3740000
0G
0F
#3745000
1G
1F
#3750000
0G
0F
#3755000
1G
1F
#3760000
0G
0F
#3765000
1G
1F
#3770000
0G
0F
#3775000
1G
1I
1F
#3780000
0G
0F
#3785000
1G
0I
1F
15
1A
#3790000
0G
0F
#3795000
1G
1F
#3800000
0G
0F
#3805000
1G
1F
#3810000
0G
0F
#3815000
1G
1F
#3820000
0G
0F
#3825000
1G
1F
#3830000
0G
0F
#3835000
1G
1F
#3840000
0G
0F
#3845000
1G
1F
#3850000
0G
0F
#3855000
1G
1F
#3860000
0G
0F
#3865000
1G
1F
#3870000
0G
0F
#3875000
1G
1F
#3880000
0G
0F
#3885000
1G
1F
#3890000
0G
0F
#3895000
1G
1F
#3900000
0G
0F
#3905000
1G
1F
#3910000
0G
0F
#3915000
1G
1F
#3920000
0G
0F
#3925000
1G
1F
#3930000
0G
0F
#3935000
1G
1I
1F
#3940000
0G
0F
#3945000
1G
0I
1F
05
#3950000
0G
0F
#3955000
1G
1F
#3960000
0G
0F
#3965000
1G
1F
#3970000
0G
0F
#3975000
1G
1F
#3980000
0G
0F
#3985000
1G
1F
#3990000
0G
0F
#3995000
1G
1F
#4000000
0G
0F
#4005000
1G
1F
#4010000
0G
0F
#4015000
1G
1F
#4020000
0G
0F
#4025000
1G
1F
#4030000
0G
0F
#4035000
1G
1F
#4040000
0G
0F
#4045000
1G
1F
#4050000
0G
0F
#4055000
1G
1F
#4060000
0G
0F
#4065000
1G
1F
#4070000
0G
0F
#4075000
1G
1F
#4080000
0G
0F
#4085000
1G
1F
#4090000
0G
0F
#4095000
1G
1I
1F
#4100000
0G
0F
#4105000
1G
0I
1F
15
16
#4110000
0G
0F
#4115000
1G
1F
#4120000
0G
0F
#4125000
1G
1F
#4130000
0G
0F
#4135000
1G
1F
#4140000
0G
0F
#4145000
1G
1F
#4150000
0G
0F
#4155000
1G
1F
#4160000
0G
0F
#4165000
1G
1F
#4170000
0G
0F
#4175000
1G
1F
#4180000
0G
0F
#4185000
1G
1F
#4190000
0G
0F
#4195000
1G
1F
#4200000
0G
0F
#4205000
1G
1F
#4210000
0G
0F
#4215000
1G
1F
#4220000
0G
0F
#4225000
1G
1F
#4230000
0G
0F
#4235000
1G
1F
#4240000
0G
0F
#4245000
1G
1F
#4250000
0G
0F
#4255000
1G
1I
1F
#4260000
0G
0F
#4265000
1G
0I
1F
#4270000
0G
0F
#4275000
1G
1F
#4280000
0G
0F
#4285000
1G
1F
#4290000
0G
0F
#4295000
1G
1F
#4300000
0G
0F
#4305000
1G
1F
#4310000
0G
0F
#4315000
1G
1F
#4320000
0G
0F
#4325000
1G
1F
#4330000
0G
0F
#4335000
1G
1F
#4340000
0G
0F
#4345000
1G
1F
#4350000
0G
0F
#4355000
1G
1F
#4360000
0G
0F
#4365000
1G
1F
#4370000
0G
0F
#4375000
1G
1F
#4380000
0G
0F
#4385000
1G
1F
#4390000
0G
0F
#4395000
1G
1F
#4400000
0G
0F
#4405000
1G
1F
#4410000
0G
0F
#4415000
1G
1I
1F
#4420000
0G
0F
#4425000
1G
0I
1F
#4430000
0G
0F
#4435000
1G
1F
#4440000
0G
0F
#4445000
1G
1F
#4450000
0G
0F
#4455000
1G
1F
#4460000
0G
0F
#4465000
1G
1F
#4470000
0G
0F
#4475000
1G
1F
#4480000
0G
0F
#4485000
1G
1F
#4490000
0G
0F
#4495000
1G
1F
#4500000
0G
0F
#4505000
1G
1F
#4510000
0G
0F
#4515000
1G
1F
#4520000
0G
0F
#4525000
1G
1F
#4530000
0G
0F
#4535000
1G
1F
#4540000
0G
0F
#4545000
1G
1F
#4550000
0G
0F
#4555000
1G
1F
#4560000
0G
0F
#4565000
1G
1F
#4570000
0G
0F
#4575000
1G
1I
1F
#4580000
0G
0F
#4585000
1G
0I
1F
#4590000
0G
0F
#4595000
1G
1F
#4600000
0G
0F
#4605000
1G
1F
#4610000
0G
0F
#4615000
1G
1F
#4620000
0G
0F
#4625000
1G
1F
#4630000
0G
0F
#4635000
1G
1F
#4640000
0G
0F
#4645000
1G
1F
#4650000
0G
0F
#4655000
1G
1F
#4660000
0G
0F
#4665000
1G
1F
#4670000
0G
0F
#4675000
1G
1F
#4680000
0G
0F
#4685000
1G
1F
#4690000
0G
0F
#4695000
1G
1F
#4700000
0G
0F
#4705000
1G
1F
