clkUnit/diviseurClk.vhd
library IEEE;
use IEEE.std_logic_1164.all;

entity diviseurClk is
  generic(facteur : natural);
  port (
    clk, reset : in  std_logic;
    nclk       : out std_logic);
end diviseurClk;

architecture arch_divClk of diviseurClk is

  signal top : std_logic := '0';
  
begin  

  div : process (clk, reset)
    variable cpt : integer range 0 to facteur-1 := 0;
  begin 
    if reset = '0' then
      nclk <= '0';
      cpt := 0;
    elsif rising_edge(clk) then
      if(cpt = facteur - 1) then
        cpt := 0;
      else
        cpt := cpt + 1;
      end if;
      if cpt = 0 then
        nclk <= '1';
      else
        nclk <= '0';
      end if;
    end if;
  end process;

end arch_divClk;

UART_RANCOULE_PICARD/clkUnit/clkUnit.vhd
library IEEE;
use IEEE.std_logic_1164.all;

entity clkUnit is

  
 port (
   clk, reset : in  std_logic;
   enableTX   : out std_logic;
   enableRX   : out std_logic);
    
end clkUnit;

architecture behavorial of clkUnit is

  component diviseurClk is
    generic (facteur : natural);
    port (
      clk, reset : in  std_logic;
      nclk       : out std_logic);
  end component diviseurClk;

begin

  inst_div : diviseurClk
  generic map (16)
    port map (
      clk   => clk,
      reset => reset,
      nclk  => enableTX);

  enableRX <= clk;
end behavorial;

TxUnit/TxUnit.vhd
LIBRARY IEEE;
USE IEEE.std_logic_1164.ALL;

ENTITY TxUnit IS
  PORT (
    clk, reset : IN STD_LOGIC;
    enable : IN STD_LOGIC;
    ld : IN STD_LOGIC;
    txd : OUT STD_LOGIC;
    regE : OUT STD_LOGIC;
    bufE : OUT STD_LOGIC;
    data : IN STD_LOGIC_VECTOR(7 DOWNTO 0));
END TxUnit;

ARCHITECTURE behavorial OF TxUnit IS

  TYPE t_etat IS (IDLE, BUFFERCHARGE, REGISTRECHARGE, ENVOIBIT, FINENVOI);
  SIGNAL etat : t_etat;
  SIGNAL bufferT : STD_LOGIC_VECTOR(7 DOWNTO 0);
  SIGNAL registerT : STD_LOGIC_VECTOR(7 DOWNTO 0);
BEGIN

  PROCESS (clk, reset)
    VARIABLE cpt : INTEGER := 0;
    VARIABLE save_buffE : STD_LOGIC;
  BEGIN
    IF (reset = '0') THEN
      etat <= IDLE;
      regE <= '1';
      bufE <= '1';
      save_buffE := '0';
      txd <= '1';
    ELSIF (rising_edge(clk)) THEN
      CASE etat IS
        WHEN IDLE =>
          IF (ld = '1') THEN
            bufferT <= data;
            bufE <= '0';
            save_buffE := '0';
            etat <= BUFFERCHARGE;
          END IF;

        WHEN BUFFERCHARGE =>
          registerT <= bufferT;
          regE <= '0';
          bufE <= '1';
          save_buffE := '1';
          etat <= REGISTRECHARGE;

        WHEN REGISTRECHARGE =>
          IF (save_buffE = '1' AND ld = '1') THEN
            bufferT <= data;
            bufE <= '0';
            save_buffE := '0';
          END IF;

          IF (enable = '1') THEN
            txd <= '0';
            cpt := 7;
            etat <= ENVOIBIT;
          END IF;

        WHEN ENVOIBIT =>
          IF (save_buffE = '1' AND ld = '1') THEN
            bufferT <= data;
            bufE <= '0';
            save_buffE := '0';
          END IF;

          IF (enable = '1') THEN

            IF (cpt = 0) THEN
              txd <= registerT(cpt);
              
              etat <= FINENVOI;
            ELSE
              txd <= registerT(cpt);
              cpt := cpt - 1;
            END IF;
          END IF;

        WHEN FINENVOI =>
          IF (save_buffE = '1' AND ld = '1') THEN
            bufferT <= data;
            bufE <= '0';
            save_buffE := '0';
          END IF;

          IF (enable = '1' AND save_buffE = '1') THEN
            txd <= '1';
            etat <= IDLE;
            regE <= '1';

          ELSIF (enable = '1' AND save_buffE = '0') THEN
            txd <= '1';
            etat <= BUFFERCHARGE;
            regE <= '1';
          END IF;

        WHEN OTHERS =>
          etat <= IDLE;

      END CASE;
    END IF;
  END PROCESS;
END behavorial;

TxUnit/testTxUnit.vhd
--------------------------------------------------------------------------------
-- Company: 
-- Engineer:
--
-- Create Date:   12:09:49 10/31/2018
-- Design Name:   
-- Module Name:   testTxUnit.vhd
-- Project Name:  uart
-- Target Device:  
-- Tool versions:  
-- Description:   
-- 
-- VHDL Test Bench Created by ISE for module: TxUnit
-- 
-- Dependencies:
-- 
-- Revision:
-- Revision 0.01 - File Created
-- Additional Comments:
--
-- Notes: 
-- This testbench has been automatically generated using types std_logic and
-- std_logic_vector for the ports of the unit under test.  Xilinx recommends
-- that these types always be used for the top-level I/O of a design in order
-- to guarantee that the testbench will bind correctly to the post-implementation 
-- simulation model.
--------------------------------------------------------------------------------
LIBRARY ieee;
USE ieee.std_logic_1164.ALL;

-- Uncomment the following library declaration if using
-- arithmetic functions with Signed or Unsigned values
--USE ieee.numeric_std.ALL;

ENTITY testTxUnit IS
END testTxUnit;

ARCHITECTURE behavior OF testTxUnit IS

  -- Component Declaration for the Unit Under Test (UUT)

  COMPONENT TxUnit
    PORT (
      clk : IN STD_LOGIC;
      reset : IN STD_LOGIC;
      enable : IN STD_LOGIC;
      ld : IN STD_LOGIC;
      txd : OUT STD_LOGIC;
      regE : OUT STD_LOGIC;
      bufE : OUT STD_LOGIC;
      data : IN STD_LOGIC_VECTOR(7 DOWNTO 0)
    );
  END COMPONENT;

  COMPONENT clkUnit
    PORT (
      clk : IN STD_LOGIC;
      reset : IN STD_LOGIC;
      enableTX : OUT STD_LOGIC;
      enableRX : OUT STD_LOGIC
    );
  END COMPONENT;

  SIGNAL clk : STD_LOGIC := '0';
  SIGNAL reset : STD_LOGIC := '0';
  SIGNAL enableTx : STD_LOGIC := '0';
  SIGNAL enableRx : STD_LOGIC := '0';
  SIGNAL ld : STD_LOGIC := '0';
  SIGNAL data : STD_LOGIC_VECTOR(7 DOWNTO 0) := (OTHERS => '0');

  SIGNAL txd : STD_LOGIC;
  SIGNAL regE : STD_LOGIC;
  SIGNAL bufE : STD_LOGIC;

  -- Clock period definitions
  CONSTANT clk_period : TIME := 10 ns;

BEGIN

  -- Instantiate the Unit Under Test
  uut0 : TxUnit PORT MAP(
    clk => clk,
    reset => reset,
    enable => enableTX,
    ld => ld,
    txd => txd,
    regE => regE,
    bufE => bufE,
    data => data
  );

  -- Instantiate the clkUnit
  clkUnit1 : clkUnit PORT MAP(
    clk => clk,
    reset => reset,
    enableTX => enableTX,
    enableRX => enableRX
  );

  -- Clock process definitions
  clk_process : PROCESS
  BEGIN
    clk <= '0';
    WAIT FOR clk_period/2;
    clk <= '1';
    WAIT FOR clk_period/2;
  END PROCESS;
  -- Stimulus process
  stim_proc : PROCESS
  BEGIN
    -- maintien du reset durant 100 ns.
    WAIT FOR 100 ns;
    reset <= '1';

    WAIT FOR 200 ns;

    -- l'émetteur est dispo ?
    IF NOT (regE = '1' AND bufE = '1') THEN
      WAIT UNTIL regE = '1' AND bufE = '1';
    END IF;

    -- si oui, on charge la donnée
    WAIT FOR clk_period;
    -- émission du caractère 0x55
    data <= "01010101";
    ld <= '1';

    -- on attend de voir que l'ordre d'émission
    -- a été bien pris en compte avant de rabaisser
    -- le signal ld
    IF NOT (regE = '1' AND bufE = '0') THEN
      WAIT UNTIL regE = '1' AND bufE = '0';
    END IF;
    WAIT FOR clk_period;
    ld <= '0';

    ----------------------------------------------------------------------------------------------------------

    -- compléter avec des tests qui montrent que la prise en compte de la demande d'émission
    -- d'un autre caractère se fait lorsqu'on émet un caractère et ceci quelque soit
    -- l'étape d'émission
    WAIT FOR 2000 ns;

    reset <= '0';

    WAIT FOR 100 ns;
    reset <= '1';

    WAIT FOR 200 ns;

    -- l'émetteur est dispo ?
    IF NOT (regE = '1' AND bufE = '1') THEN
      WAIT UNTIL regE = '1' AND bufE = '1';
    END IF;

    -- si oui, on charge la donnée
    WAIT FOR clk_period;
    -- émission du caractère 0x55
    data <= "01010101";
    ld <= '1';

    -- on attend de voir que l'ordre d'émission
    -- a été bien pris en compte avant de rabaisser
    -- le signal ld
    IF NOT (regE = '1' AND bufE = '0') THEN
      WAIT UNTIL regE = '1' AND bufE = '0';
    END IF;
    WAIT FOR clk_period;
    ld <= '0';

    IF NOT (regE = '0' AND bufE = '1') THEN
      WAIT UNTIL regE = '0' AND bufE = '1';
    END IF;

    WAIT FOR clk_period;

    data <= "11111111";
    WAIT FOR clk_period;
    ld <= '1';
    WAIT FOR clk_period;
    ld <= '0';


    ------------------------------------------------------------------------------------------------

    WAIT FOR 5000 ns;

    reset <= '0';

    WAIT FOR 100 ns;
    reset <= '1';

    WAIT FOR 200 ns;

    -- l'émetteur est dispo ?
    IF NOT (regE = '1' AND bufE = '1') THEN
      WAIT UNTIL regE = '1' AND bufE = '1';
    END IF;

    -- si oui, on charge la donnée
    WAIT FOR clk_period;
    -- émission du caractère 0x55
    data <= "01010101";
    ld <= '1';

    -- on attend de voir que l'ordre d'émission
    -- a été bien pris en compte avant de rabaisser
    -- le signal ld
    IF NOT (regE = '1' AND bufE = '0') THEN
      WAIT UNTIL regE = '1' AND bufE = '0';
    END IF;
    WAIT FOR clk_period;
    ld <= '0';

    IF NOT (regE = '0' AND bufE = '1') THEN
      WAIT UNTIL regE = '0' AND bufE = '1';
    END IF;

    WAIT FOR clk_period;

    data <= "11111111";
    WAIT FOR clk_period;
    ld <= '1';
    WAIT FOR clk_period;
    ld <= '0';

    WAIT FOR clk_period * 10;
    

    data <= "11101111";
    WAIT FOR clk_period;
    ld <= '1';
    WAIT FOR clk_period;
    ld <= '0';

    WAIT;

  END PROCESS;

END;

UART_RANCOULE_PICARD/TxUnit/output.vcd
$date
   Fri Jan 19 17:17:35 2024
$end
$version
  P.20131013
$end
$timescale
  1ps
$end
$scope module testtxunit $end
$var wire 1 U clk $end
$var wire 1 V reset $end
$var wire 1 W enabletx $end
$var wire 1 T enablerx $end
$var wire 1 4 ld $end
$var wire 1 ? data [7] $end
$var wire 1 > data [6] $end
$var wire 1 = data [5] $end
$var wire 1 < data [4] $end
$var wire 1 ; data [3] $end
$var wire 1 : data [2] $end
$var wire 1 9 data [1] $end
$var wire 1 8 data [0] $end
$var wire 1 5 txd $end
$var wire 1 6 rege $end
$var wire 1 7 bufe $end
$scope module uut0 $end
$var wire 1 U clk $end
$var wire 1 V reset $end
$var wire 1 W enable $end
$var wire 1 4 ld $end
$var wire 1 5 txd $end
$var wire 1 6 rege $end
$var wire 1 7 bufe $end
$var wire 1 ? data [7] $end
$var wire 1 > data [6] $end
$var wire 1 = data [5] $end
$var wire 1 < data [4] $end
$var wire 1 ; data [3] $end
$var wire 1 : data [2] $end
$var wire 1 9 data [1] $end
$var wire 1 8 data [0] $end
$var wire 1 H buffert [7] $end
$var wire 1 G buffert [6] $end
$var wire 1 F buffert [5] $end
$var wire 1 E buffert [4] $end
$var wire 1 D buffert [3] $end
$var wire 1 C buffert [2] $end
$var wire 1 B buffert [1] $end
$var wire 1 A buffert [0] $end
$var wire 1 P registert [7] $end
$var wire 1 O registert [6] $end
$var wire 1 N registert [5] $end
$var wire 1 M registert [4] $end
$var wire 1 L registert [3] $end
$var wire 1 K registert [2] $end
$var wire 1 J registert [1] $end
$var wire 1 I registert [0] $end
$upscope $end
$scope module clkUnit1 $end
$var wire 1 U clk $end
$var wire 1 V reset $end
$var wire 1 W enabletx $end
$var wire 1 T enablerx $end
$scope module inst_div $end
$var wire 1 U clk $end
$var wire 1 V reset $end
$var wire 1 W nclk $end
$var wire 1 X top $end
$upscope $end
$upscope $end
$upscope $end
$enddefinitions $end
#0
$dumpvars
0U
0V
0W
0T
04
0?
0>
0=
0<
0;
0:
09
08
15
16
17
xH
xG
xF
xE
xD
xC
xB
xA
xP
xO
xN
xM
xL
xK
xJ
xI
0X
$end
#5000
1U
1T
#10000
0U
0T
#15000
1U
1T
#20000
0U
0T
#25000
1U
1T
#30000
0U
0T
#35000
1U
1T
#40000
0U
0T
#45000
1U
1T
#50000
0U
0T
#55000
1U
1T
#60000
0U
0T
#65000
1U
1T
#70000
0U
0T
#75000
1U
1T
#80000
0U
0T
#85000
1U
1T
#90000
0U
0T
#95000
1U
1T
#100000
0U
1V
0T
#105000
1U
1T
#110000
0U
0T
#115000
1U
1T
#120000
0U
0T
#125000
1U
1T
#130000
0U
0T
#135000
1U
1T
#140000
0U
0T
#145000
1U
1T
#150000
0U
0T
#155000
1U
1T
#160000
0U
0T
#165000
1U
1T
#170000
0U
0T
#175000
1U
1T
#180000
0U
0T
#185000
1U
1T
#190000
0U
0T
#195000
1U
1T
#200000
0U
0T
#205000
1U
1T
#210000
0U
0T
#215000
1U
1T
#220000
0U
0T
#225000
1U
1T
#230000
0U
0T
#235000
1U
1T
#240000
0U
0T
#245000
1U
1T
#250000
0U
0T
#255000
1U
1W
1T
#260000
0U
0T
#265000
1U
0W
1T
#270000
0U
0T
#275000
1U
1T
#280000
0U
0T
#285000
1U
1T
#290000
0U
0T
#295000
1U
1T
#300000
0U
0T
#305000
1U
1T
#310000
0U
0T
14
1>
1<
1:
18
#315000
1U
1T
07
0H
1G
0F
1E
0D
1C
0B
1A
#320000
0U
0T
#325000
1U
1T
04
06
17
0P
1O
0N
1M
0L
1K
0J
1I
#330000
0U
0T
#335000
1U
1T
#340000
0U
0T
#345000
1U
1T
#350000
0U
0T
#355000
1U
1T
#360000
0U
0T
#365000
1U
1T
#370000
0U
0T
#375000
1U
1T
#380000
0U
0T
#385000
1U
1T
#390000
0U
0T
#395000
1U
1T
#400000
0U
0T
#405000
1U
1T
#410000
0U
0T
#415000
1U
1W
1T
#420000
0U
0T
#425000
1U
0W
1T
05
#430000
0U
0T
#435000
1U
1T
#440000
0U
0T
#445000
1U
1T
#450000
0U
0T
#455000
1U
1T
#460000
0U
0T
#465000
1U
1T
#470000
0U
0T
#475000
1U
1T
#480000
0U
0T
#485000
1U
1T
#490000
0U
0T
#495000
1U
1T
#500000
0U
0T
#505000
1U
1T
#510000
0U
0T
#515000
1U
1T
#520000
0U
0T
#525000
1U
1T
#530000
0U
0T
#535000
1U
1T
#540000
0U
0T
#545000
1U
1T
#550000
0U
0T
#555000
1U
1T
#560000
0U
0T
#565000
1U
1T
#570000
0U
0T
#575000
1U
1W
1T
#580000
0U
0T
#585000
1U
0W
1T
#590000
0U
0T
#595000
1U
1T
#600000
0U
0T
#605000
1U
1T
#610000
0U
0T
#615000
1U
1T
#620000
0U
0T
#625000
1U
1T
#630000
0U
0T
#635000
1U
1T
#640000
0U
0T
#645000
1U
1T
#650000
0U
0T
#655000
1U
1T
#660000
0U
0T
#665000
1U
1T
#670000
0U
0T
#675000
1U
1T
#680000
0U
0T
#685000
1U
1T
#690000
0U
0T
#695000
1U
1T
#700000
0U
0T
#705000
1U
1T
#710000
0U
0T
#715000
1U
1T
#720000
0U
0T
#725000
1U
1T
#730000
0U
0T
#735000
1U
1W
1T
#740000
0U
0T
#745000
1U
0W
1T
15
#750000
0U
0T
#755000
1U
1T
#760000
0U
0T
#765000
1U
1T
#770000
0U
0T
#775000
1U
1T
#780000
0U
0T
#785000
1U
1T
#790000
0U
0T
#795000
1U
1T
#800000
0U
0T
#805000
1U
1T
#810000
0U
0T
#815000
1U
1T
#820000
0U
0T
#825000
1U
1T
#830000
0U
0T
#835000
1U
1T
#840000
0U
0T
#845000
1U
1T
#850000
0U
0T
#855000
1U
1T
#860000
0U
0T
#865000
1U
1T
#870000
0U
0T
#875000
1U
1T
#880000
0U
0T
#885000
1U
1T
#890000
0U
0T
#895000
1U
1W
1T
#900000
0U
0T
#905000
1U
0W
1T
05
#910000
0U
0T
#915000
1U
1T
#920000
0U
0T
#925000
1U
1T
#930000
0U
0T
#935000
1U
1T
#940000
0U
0T
#945000
1U
1T
#950000
0U
0T
#955000
1U
1T
#960000
0U
0T
#965000
1U
1T
#970000
0U
0T
#975000
1U
1T
#980000
0U
0T
#985000
1U
1T
#990000
0U
0T
#995000
1U
1T
#1000000
0U
0T
#1005000
1U
1T
#1010000
0U
0T
#1015000
1U
1T
#1020000
0U
0T
#1025000
1U
1T
#1030000
0U
0T
#1035000
1U
1T
#1040000
0U
0T
#1045000
1U
1T
#1050000
0U
0T
#1055000
1U
1W
1T
#1060000
0U
0T
#1065000
1U
0W
1T
15
#1070000
0U
0T
#1075000
1U
1T
#1080000
0U
0T
#1085000
1U
1T
#1090000
0U
0T
#1095000
1U
1T
#1100000
0U
0T
#1105000
1U
1T
#1110000
0U
0T
#1115000
1U
1T
#1120000
0U
0T
#1125000
1U
1T
#1130000
0U
0T
#1135000
1U
1T
#1140000
0U
0T
#1145000
1U
1T
#1150000
0U
0T
#1155000
1U
1T
#1160000
0U
0T
#1165000
1U
1T
#1170000
0U
0T
#1175000
1U
1T
#1180000
0U
0T
#1185000
1U
1T
#1190000
0U
0T
#1195000
1U
1T
#1200000
0U
0T
#1205000
1U
1T
#1210000
0U
0T
#1215000
1U
1W
1T
#1220000
0U
0T
#1225000
1U
0W
1T
05
#1230000
0U
0T
#1235000
1U
1T
#1240000
0U
0T
#1245000
1U
1T
#1250000
0U
0T
#1255000
1U
1T
#1260000
0U
0T
#1265000
1U
1T
#1270000
0U
0T
#1275000
1U
1T
#1280000
0U
0T
#1285000
1U
1T
#1290000
0U
0T
#1295000
1U
1T
#1300000
0U
0T
#1305000
1U
1T
#1310000
0U
0T
#1315000
1U
1T
#1320000
0U
0T
#1325000
1U
1T
#1330000
0U
0T
#1335000
1U
1T
#1340000
0U
0T
#1345000
1U
1T
#1350000
0U
0T
#1355000
1U
1T
#1360000
0U
0T
#1365000
1U
1T
#1370000
0U
0T
#1375000
1U
1W
1T
#1380000
0U
0T
#1385000
1U
0W
1T
15
#1390000
0U
0T
#1395000
1U
1T
#1400000
0U
0T
#1405000
1U
1T
#1410000
0U
0T
#1415000
1U
1T
#1420000
0U
0T
#1425000
1U
1T
#1430000
0U
0T
#1435000
1U
1T
#1440000
0U
0T
#1445000
1U
1T
#1450000
0U
0T
#1455000
1U
1T
#1460000
0U
0T
#1465000
1U
1T
#1470000
0U
0T
#1475000
1U
1T
#1480000
0U
0T
#1485000
1U
1T
#1490000
0U
0T
#1495000
1U
1T
#1500000
0U
0T
#1505000
1U
1T
#1510000
0U
0T
#1515000
1U
1T
#1520000
0U
0T
#1525000
1U
1T
#1530000
0U
0T
#1535000
1U
1W
1T
#1540000
0U
0T
#1545000
1U
0W
1T
05
#1550000
0U
0T
#1555000
1U
1T
#1560000
0U
0T
#1565000
1U
1T
#1570000
0U
0T
#1575000
1U
1T
#1580000
0U
0T
#1585000
1U
1T
#1590000
0U
0T
#1595000
1U
1T
#1600000
0U
0T
#1605000
1U
1T
#1610000
0U
0T
#1615000
1U
1T
#1620000
0U
0T
#1625000
1U
1T
#1630000
0U
0T
#1635000
1U
1T
#1640000
0U
0T
#1645000
1U
1T
#1650000
0U
0T
#1655000
1U
1T
#1660000
0U
0T
#1665000
1U
1T
#1670000
0U
0T
#1675000
1U
1T
#1680000
0U
0T
#1685000
1U
1T
#1690000
0U
0T
#1695000
1U
1W
1T
#1700000
0U
0T
#1705000
1U
0W
1T
15
#1710000
0U
0T
#1715000
1U
1T
#1720000
0U
0T
#1725000
1U
1T
#1730000
0U
0T
#1735000
1U
1T
#1740000
0U
0T
#1745000
1U
1T
#1750000
0U
0T
#1755000
1U
1T
#1760000
0U
0T
#1765000
1U
1T
#1770000
0U
0T
#1775000
1U
1T
#1780000
0U
0T
#1785000
1U
1T
#1790000
0U
0T
#1795000
1U
1T
#1800000
0U
0T
#1805000
1U
1T
#1810000
0U
0T
#1815000
1U
1T
#1820000
0U
0T
#1825000
1U
1T
#1830000
0U
0T
#1835000
1U
1T
#1840000
0U
0T
#1845000
1U
1T
#1850000
0U
0T
#1855000
1U
1W
1T
#1860000
0U
0T
#1865000
1U
0W
1T
16
#1870000
0U
0T
#1875000
1U
1T
#1880000
0U
0T
#1885000
1U
1T
#1890000
0U
0T
#1895000
1U
1T
#1900000
0U
0T
#1905000
1U
1T
#1910000
0U
0T
#1915000
1U
1T
#1920000
0U
0T
#1925000
1U
1T
#1930000
0U
0T
#1935000
1U
1T
#1940000
0U
0T
#1945000
1U
1T
#1950000
0U
0T
#1955000
1U
1T
#1960000
0U
0T
#1965000
1U
1T
#1970000
0U
0T
#1975000
1U
1T
#1980000
0U
0T
#1985000
1U
1T
#1990000
0U
0T
#1995000
1U
1T
#2000000
0U
0T
#2005000
1U
1T
#2010000
0U
0T
#2015000
1U
1W
1T
#2020000
0U
0T
#2025000
1U
0W
1T
#2030000
0U
0T
#2035000
1U
1T
#2040000
0U
0T
#2045000
1U
1T
#2050000
0U
0T
#2055000
1U
1T
#2060000
0U
0T
#2065000
1U
1T
#2070000
0U
0T
#2075000
1U
1T
#2080000
0U
0T
#2085000
1U
1T
#2090000
0U
0T
#2095000
1U
1T
#2100000
0U
0T
#2105000
1U
1T
#2110000
0U
0T
#2115000
1U
1T
#2120000
0U
0T
#2125000
1U
1T
#2130000
0U
0T
#2135000
1U
1T
#2140000
0U
0T
#2145000
1U
1T
#2150000
0U
0T
#2155000
1U
1T
#2160000
0U
0T
#2165000
1U
1T
#2170000
0U
0T
#2175000
1U
1W
1T
#2180000
0U
0T
#2185000
1U
0W
1T
#2190000
0U
0T
#2195000
1U
1T
#2200000
0U
0T
#2205000
1U
1T
#2210000
0U
0T
#2215000
1U
1T
#2220000
0U
0T
#2225000
1U
1T
#2230000
0U
0T
#2235000
1U
1T
#2240000
0U
0T
#2245000
1U
1T
#2250000
0U
0T
#2255000
1U
1T
#2260000
0U
0T
#2265000
1U
1T
#2270000
0U
0T
#2275000
1U
1T
#2280000
0U
0T
#2285000
1U
1T
#2290000
0U
0T
#2295000
1U
1T
#2300000
0U
0T
#2305000
1U
1T
#2310000
0U
0T
#2315000
1U
1T
#2320000
0U
0T
#2325000
1U
0V
1T
#2330000
0U
0T
#2335000
1U
1T
#2340000
0U
0T
#2345000
1U
1T
#2350000
0U
0T
#2355000
1U
1T
#2360000
0U
0T
#2365000
1U
1T
#2370000
0U
0T
#2375000
1U
1T
#2380000
0U
0T
#2385000
1U
1T
#2390000
0U
0T
#2395000
1U
1T
#2400000
0U
0T
#2405000
1U
1T
#2410000
0U
0T
#2415000
1U
1T
#2420000
0U
0T
#2425000
1U
1V
1T
#2430000
0U
0T
#2435000
1U
1T
#2440000
0U
0T
#2445000
1U
1T
#2450000
0U
0T
#2455000
1U
1T
#2460000
0U
0T
#2465000
1U
1T
#2470000
0U
0T
#2475000
1U
1T
#2480000
0U
0T
#2485000
1U
1T
#2490000
0U
0T
#2495000
1U
1T
#2500000
0U
0T
#2505000
1U
1T
#2510000
0U
0T
#2515000
1U
1T
#2520000
0U
0T
#2525000
1U
1T
#2530000
0U
0T
#2535000
1U
1T
#2540000
0U
0T
#2545000
1U
1T
#2550000
0U
0T
#2555000
1U
1T
#2560000
0U
0T
#2565000
1U
1T
#2570000
0U
0T
#2575000
1U
1W
1T
#2580000
0U
0T
#2585000
1U
0W
1T
#2590000
0U
0T
#2595000
1U
1T
#2600000
0U
0T
#2605000
1U
1T
#2610000
0U
0T
#2615000
1U
1T
#2620000
0U
0T
#2625000
1U
1T
#2630000
0U
0T
#2635000
1U
1T
14
07
#2640000
0U
0T
#2645000
1U
1T
04
06
17
#2650000
0U
0T
#2655000
1U
1T
1?
1=
1;
19
#2660000
0U
0T
#2665000
1U
1T
14
07
1H
1F
1D
1B
#2670000
0U
0T
#2675000
1U
1T
04
#2680000
0U
0T
#2685000
1U
1T
#2690000
0U
0T
#2695000
1U
1T
#2700000
0U
0T
#2705000
1U
1T
#2710000
0U
0T
#2715000
1U
1T
#2720000
0U
0T
#2725000
1U
1T
#2730000
0U
0T
#2735000
1U
1W
1T
#2740000
0U
0T
#2745000
1U
0W
1T
05
#2750000
0U
0T
#2755000
1U
1T
#2760000
0U
0T
#2765000
1U
1T
#2770000
0U
0T
#2775000
1U
1T
#2780000
0U
0T
#2785000
1U
1T
#2790000
0U
0T
#2795000
1U
1T
#2800000
0U
0T
#2805000
1U
1T
#2810000
0U
0T
#2815000
1U
1T
#2820000
0U
0T
#2825000
1U
1T
#2830000
0U
0T
#2835000
1U
1T
#2840000
0U
0T
#2845000
1U
1T
#2850000
0U
0T
#2855000
1U
1T
#2860000
0U
0T
#2865000
1U
1T
#2870000
0U
0T
#2875000
1U
1T
#2880000
0U
0T
#2885000
1U
1T
#2890000
0U
0T
#2895000
1U
1W
1T
#2900000
0U
0T
#2905000
1U
0W
1T
#2910000
0U
0T
#2915000
1U
1T
#2920000
0U
0T
#2925000
1U
1T
#2930000
0U
0T
#2935000
1U
1T
#2940000
0U
0T
#2945000
1U
1T
#2950000
0U
0T
#2955000
1U
1T
#2960000
0U
0T
#2965000
1U
1T
#2970000
0U
0T
#2975000
1U
1T
#2980000
0U
0T
#2985000
1U
1T
#2990000
0U
0T
#2995000
1U
1T
#3000000
0U
0T
#3005000
1U
1T
#3010000
0U
0T
#3015000
1U
1T
#3020000
0U
0T
#3025000
1U
1T
#3030000
0U
0T
#3035000
1U
1T
#3040000
0U
0T
#3045000
1U
1T
#3050000
0U
0T
#3055000
1U
1W
1T
#3060000
0U
0T
#3065000
1U
0W
1T
15
#3070000
0U
0T
#3075000
1U
1T
#3080000
0U
0T
#3085000
1U
1T
#3090000
0U
0T
#3095000
1U
1T
#3100000
0U
0T
#3105000
1U
1T
#3110000
0U
0T
#3115000
1U
1T
#3120000
0U
0T
#3125000
1U
1T
#3130000
0U
0T
#3135000
1U
1T
#3140000
0U
0T
#3145000
1U
1T
#3150000
0U
0T
#3155000
1U
1T
#3160000
0U
0T
#3165000
1U
1T
#3170000
0U
0T
#3175000
1U
1T
#3180000
0U
0T
#3185000
1U
1T
#3190000
0U
0T
#3195000
1U
1T
#3200000
0U
0T
#3205000
1U
1T
#3210000
0U
0T
#3215000
1U
1W
1T
#3220000
0U
0T
#3225000
1U
0W
1T
05
#3230000
0U
0T
#3235000
1U
1T
#3240000
0U
0T
#3245000
1U
1T
#3250000
0U
0T
#3255000
1U
1T
#3260000
0U
0T
#3265000
1U
1T
#3270000
0U
0T
#3275000
1U
1T
#3280000
0U
0T
#3285000
1U
1T
#3290000
0U
0T
#3295000
1U
1T
#3300000
0U
0T
#3305000
1U
1T
#3310000
0U
0T
#3315000
1U
1T
#3320000
0U
0T
#3325000
1U
1T
#3330000
0U
0T
#3335000
1U
1T
#3340000
0U
0T
#3345000
1U
1T
#3350000
0U
0T
#3355000
1U
1T
#3360000
0U
0T
#3365000
1U
1T
#3370000
0U
0T
#3375000
1U
1W
1T
#3380000
0U
0T
#3385000
1U
0W
1T
15
#3390000
0U
0T
#3395000
1U
1T
#3400000
0U
0T
#3405000
1U
1T
#3410000
0U
0T
#3415000
1U
1T
#3420000
0U
0T
#3425000
1U
1T
#3430000
0U
0T
#3435000
1U
1T
#3440000
0U
0T
#3445000
1U
1T
#3450000
0U
0T
#3455000
1U
1T
#3460000
0U
0T
#3465000
1U
1T
#3470000
0U
0T
#3475000
1U
1T
#3480000
0U
0T
#3485000
1U
1T
#3490000
0U
0T
#3495000
1U
1T
#3500000
0U
0T
#3505000
1U
1T
#3510000
0U
0T
#3515000
1U
1T
#3520000
0U
0T
#3525000
1U
1T
#3530000
0U
0T
#3535000
1U
1W
1T
#3540000
0U
0T
#3545000
1U
0W
1T
05
#3550000
0U
0T
#3555000
1U
1T
#3560000
0U
0T
#3565000
1U
1T
#3570000
0U
0T
#3575000
1U
1T
#3580000
0U
0T
#3585000
1U
1T
#3590000
0U
0T
#3595000
1U
1T
#3600000
0U
0T
#3605000
1U
1T
#3610000
0U
0T
#3615000
1U
1T
#3620000
0U
0T
#3625000
1U
1T
#3630000
0U
0T
#3635000
1U
1T
#3640000
0U
0T
#3645000
1U
1T
#3650000
0U
0T
#3655000
1U
1T
#3660000
0U
0T
#3665000
1U
1T
#3670000
0U
0T
#3675000
1U
1T
#3680000
0U
0T
#3685000
1U
1T
#3690000
0U
0T
#3695000
1U
1W
1T
#3700000
0U
0T
#3705000
1U
0W
1T
15
#3710000
0U
0T
#3715000
1U
1T
#3720000
0U
0T
#3725000
1U
1T
#3730000
0U
0T
#3735000
1U
1T
#3740000
0U
0T
#3745000
1U
1T
#3750000
0U
0T
#3755000
1U
1T
#3760000
0U
0T
#3765000
1U
1T
#3770000
0U
0T
#3775000
1U
1T
#3780000
0U
0T
#3785000
1U
1T
#3790000
0U
0T
#3795000
1U
1T
#3800000
0U
0T
#3805000
1U
1T
#3810000
0U
0T
#3815000
1U
1T
#3820000
0U
0T
#3825000
1U
1T
#3830000
0U
0T
#3835000
1U
1T
#3840000
0U
0T
#3845000
1U
1T
#3850000
0U
0T
#3855000
1U
1W
1T
#3860000
0U
0T
#3865000
1U
0W
1T
05
#3870000
0U
0T
#3875000
1U
1T
#3880000
0U
0T
#3885000
1U
1T
#3890000
0U
0T
#3895000
1U
1T
#3900000
0U
0T
#3905000
1U
1T
#3910000
0U
0T
#3915000
1U
1T
#3920000
0U
0T
#3925000
1U
1T
#3930000
0U
0T
#3935000
1U
1T
#3940000
0U
0T
#3945000
1U
1T
#3950000
0U
0T
#3955000
1U
1T
#3960000
0U
0T
#3965000
1U
1T
#3970000
0U
0T
#3975000
1U
1T
#3980000
0U
0T
#3985000
1U
1T
#3990000
0U
0T
#3995000
1U
1T
#4000000
0U
0T
#4005000
1U
1T
#4010000
0U
0T
#4015000
1U
1W
1T
#4020000
0U
0T
#4025000
1U
0W
1T
15
#4030000
0U
0T
#4035000
1U
1T
#4040000
0U
0T
#4045000
1U
1T
#4050000
0U
0T
#4055000
1U
1T
#4060000
0U
0T
#4065000
1U
1T
#4070000
0U
0T
#4075000
1U
1T
#4080000
0U
0T
#4085000
1U
1T
#4090000
0U
0T
#4095000
1U
1T
#4100000
0U
0T
#4105000
1U
1T
#4110000
0U
0T
#4115000
1U
1T
#4120000
0U
0T
#4125000
1U
1T
#4130000
0U
0T
#4135000
1U
1T
#4140000
0U
0T
#4145000
1U
1T
