clkUnit/diviseurClk.vhd
library IEEE;
use IEEE.std_logic_1164.all;

entity diviseurClk is
  generic(facteur : natural);
  port (
    clk, reset : in  std_logic;
    nclk       : out std_logic);
end diviseurClk;

architecture arch_divClk of diviseurClk is

  signal top : std_logic := '0';
  
begin  

  div : process (clk, reset)
    variable cpt : integer range 0 to facteur-1 := 0;
  begin 
    if reset = '0' then
      nclk <= '0';
      cpt := 0;
    elsif rising_edge(clk) then
      if(cpt = facteur - 1) then
        cpt := 0;
      else
        cpt := cpt + 1;
      end if;
      if cpt = 0 then
        nclk <= '1';
      else
        nclk <= '0';
      end if;
    end if;
  end process;

end arch_divClk;

UART_RANCOULE_PICARD/clkUnit/clkUnit.vhd
library IEEE;
use IEEE.std_logic_1164.all;

entity clkUnit is

  
 port (
   clk, reset : in  std_logic;
   enableTX   : out std_logic;
   enableRX   : out std_logic);
    
end clkUnit;

architecture behavorial of clkUnit is

  component diviseurClk is
    generic (facteur : natural);
    port (
      clk, reset : in  std_logic;
      nclk       : out std_logic);
  end component diviseurClk;

begin

  inst_div : diviseurClk
  generic map (16)
    port map (
      clk   => clk,
      reset => reset,
      nclk  => enableTX);

  enableRX <= clk;
end behavorial;

UART_Emission/EltEtat.vhd
----------------------------------------------------------------------------------
-- Company: 
-- Engineer: 
-- 
-- Create Date:    14:30:11 12/19/2023 
-- Design Name: 
-- Module Name:    EltEtat - Behavioral 
-- Project Name: 
-- Target Devices: 
-- Tool versions: 
-- Description: 
--
-- Dependencies: 
--
-- Revision: 
-- Revision 0.01 - File Created
-- Additional Comments: 
--
----------------------------------------------------------------------------------
LIBRARY IEEE;
USE IEEE.STD_LOGIC_1164.ALL;

-- Uncomment the following library declaration if using
-- arithmetic functions with Signed or Unsigned values
--use IEEE.NUMERIC_STD.ALL;

-- Uncomment the following library declaration if instantiating
-- any Xilinx primitives in this code.
--library UNISIM;
--use UNISIM.VComponents.all;

ENTITY EltEtat IS
  PORT (
    reset : IN STD_LOGIC;
    clk : IN STD_LOGIC;
    tmpClk : IN STD_LOGIC;
    tmpRxd : IN STD_LOGIC;
    read : IN STD_LOGIC;
    FErr : OUT STD_LOGIC;
    OErr : OUT STD_LOGIC;
    DRdy : OUT STD_LOGIC;
    data : OUT STD_LOGIC_VECTOR(7 DOWNTO 0));
END EltEtat;

ARCHITECTURE Behavioral OF EltEtat IS

  TYPE etat_type IS (init, assemblage, fin, finy);
  SIGNAL etat : etat_type := init;
  SIGNAL saveData : STD_LOGIC_VECTOR(7 DOWNTO 0);

BEGIN
  PROCESS (clk, reset, tmpClk)
    VARIABLE compteur : INTEGER RANGE 0 TO 7 := 0;
    VARIABLE compteur_ready : INTEGER RANGE 0 TO 2 := 0;

  BEGIN
    -- Réinitialisation du composant
    IF reset = '0' THEN
      etat <= init;
      data <= (OTHERS => '0');
      FErr <= '0';
      OErr <= '0';
      DRdy <= '0';
      compteur_ready := 0;
    ELSIF rising_edge(clk) THEN

      CASE etat IS
          -- Etat d'initialisation
        WHEN init =>
          FErr <= '0';
          OErr <= '0';
          compteur_ready := 0;

          

          IF tmpClk = '1' THEN
            saveData <= (OTHERS => 'U');
				    DRdy <= '0';
            etat <= assemblage;
            compteur := 0;
          END IF;

          -- Assemblage des 8 bits de données
        WHEN assemblage =>
          IF tmpClk = '1' THEN

            IF compteur = 7 THEN
              saveData(7-compteur) <= tmpRxd;
              report "Je change le bit " & integer'image(compteur) & " de saveData en " & std_logic'image(tmpRxd);              
              compteur := 0;
              etat <= fin;
            ELSE
              -- Sauvegarde des données
              saveData(7-compteur) <= tmpRxd;
              report "Je change le bit " & integer'image(compteur) & " de saveData en " & std_logic'image(tmpRxd);
              compteur := compteur + 1;
              
            END IF;

          END IF;
          -- Fin de la réception des 8 bits de données
        WHEN fin =>

          IF tmpClk = '1' THEN
            report "Je récupère le bit de fin qui est " & std_logic'image(tmpRxd);
            -- Détection de l'erreur d'envoi
            IF tmpRxd = '0' THEN
              FErr <= '1';
              DRdy <= '0';
              etat <= init;
            ELSE
              DRdy <= '1';
              data <= saveData;
              -- Détection de l'erreur de donnée

              etat <= finy;
            END IF;

          END IF;

          -- Réinitialisation de DRdy  
        WHEN finy =>

          if (compteur_ready = 2) then 
            compteur_ready := 0;

          IF read = '0' THEN
            OErr <= '1';
          END IF;
          DRdy <= '0';
          etat <= init;
          end if;

          compteur_ready := compteur_ready + 1;
        

      END CASE;
    END IF;
  END PROCESS;

END Behavioral;

UART_Emission/EltInstants.vhd
----------------------------------------------------------------------------------
-- Company: 
-- Engineer: 
-- 
-- Create Date:    14:29:27 12/19/2023 
-- Design Name: 
-- Module Name:    EltInstants - Behavioral 
-- Project Name: 
-- Target Devices: 
-- Tool versions: 
-- Description: 
--
-- Dependencies: 
--
-- Revision: 
-- Revision 0.01 - File Created
-- Additional Comments: 
--
----------------------------------------------------------------------------------
LIBRARY IEEE;
USE IEEE.STD_LOGIC_1164.ALL;

-- Uncomment the following library declaration if using
-- arithmetic functions with Signed or Unsigned values
--use IEEE.NUMERIC_STD.ALL;

-- Uncomment the following library declaration if instantiating
-- any Xilinx primitives in this code.
--library UNISIM;
--use UNISIM.VComponents.all;

ENTITY EltInstants IS
    PORT (
        enable : IN STD_LOGIC;
        reset : IN STD_LOGIC;
        Rxd : IN STD_LOGIC;
        tmpClk : OUT STD_LOGIC;
        tmpRxd : OUT STD_LOGIC
    );
END EltInstants;

ARCHITECTURE Behavioral OF EltInstants IS

    TYPE t_etat IS (init, cpt8, cpt16); -- Etats possibles du composant
    SIGNAL saveTmpClk : STD_LOGIC;
    SIGNAL etat : t_etat; -- Etat actuel du composant

BEGIN
    PROCESS (enable, reset)

        VARIABLE cpt : NATURAL; -- Compteur de cycles enable
        VARIABLE cpt_bit : NATURAL; -- Compteur de bits

    BEGIN
        -- Réinitialisation du composant
        IF reset = '0' THEN
            etat <= init;
            cpt := 0;
            cpt_bit := 0;

        ELSIF rising_edge(enable) THEN
            CASE etat IS
                    -- Etat d'initialisation
                WHEN init =>
                    tmpClk <= '0';
                    saveTmpClk <= '0';


                    -- Vérification du début de la réception
                    IF Rxd = '0' THEN
                        -- Initialisation du compteur, du bit de stop et de la clock
                        cpt := 0;
                        tmpClk <= '0';
                        saveTmpClk <= '0';
                        cpt_bit := 0;
                        etat <= cpt8;
                    END IF;

                    -- Attente de 8 cycles
                WHEN cpt8 =>
                    IF cpt >= 7 THEN
                        tmpClk <= '1';
                        saveTmpClk <= '1';
                        tmpRxd <= Rxd;
                        cpt := 0;
                        etat <= cpt16;
                    ELSE
                        -- Incrémentation du compteur
                        cpt := cpt + 1;
                    END IF;

                    -- Attente de 16 cycles
                WHEN cpt16 =>
                    tmpClk <= '0';

                    IF cpt = 15 THEN
                        
                        cpt := 0;
                        -- Vérification de la réception complète

                        tmpRxd <= Rxd;

                        saveTmpClk <= '1';
                        tmpClk <= '1';

                        IF cpt_bit = 8 THEN
                            tmpRxd <= '1';
                            etat <= init;
                        END IF;

                        cpt_bit := cpt_bit + 1;

                    ELSE
                        -- Incrémentation du compteur
                        cpt := cpt + 1;
                    END IF;

            END CASE;
        END IF;
    END PROCESS;

END Behavioral;

UART_Emission/RxUnit.vhd
----------------------------------------------------------------------------------
-- Company: 
-- Engineer: 
-- 
-- Create Date:    14:19:00 12/19/2023 
-- Design Name: 
-- Module Name:    RxUnit - Behavioral 
-- Project Name: 
-- Target Devices: 
-- Tool versions: 
-- Description: 
--
-- Dependencies: 
--
-- Revision: 
-- Revision 0.01 - File Created
-- Additional Comments: 
--
----------------------------------------------------------------------------------
library IEEE;
use IEEE.STD_LOGIC_1164.ALL;

-- Uncomment the following library declaration if using
-- arithmetic functions with Signed or Unsigned values
--use IEEE.NUMERIC_STD.ALL;

-- Uncomment the following library declaration if instantiating
-- any Xilinx primitives in this code.
--library UNISIM;
--use UNISIM.VComponents.all;

entity RxUnit is
port ( clk, reset : in std_logic ;
       enable : in std_logic ;
       read : in std_logic ;
       rxd : in std_logic ;
       data : out std_logic_vector(7 downto 0) ;
       FErr, OErr, DRdy : out std_logic );
end RxUnit ;

architecture Behavioral of RxUnit is

    component EltInstants is
        port(enable : in std_logic;
            reset : in std_logic;
            Rxd : in std_logic;
            tmpClk : out std_logic;
            tmpRxd : out std_logic
        );
    end component;

    component EltEtat is
        port (
            reset : in std_logic;
            clk : in std_logic;
            tmpClk : in std_logic;
            tmpRxd : in std_logic;
            read : in std_logic;
            FErr : out std_logic;
            OErr : out std_logic;
            DRdy : out std_logic;
            data : out std_logic_vector(7 downto 0));
    end component;

    signal tmpClk, tmpRxd, DRdy_bis : std_logic;

begin

    instants : EltInstants 
    port map(
        enable => enable, 
        reset => reset, 
        Rxd => rxd, 
        tmpClk => tmpClk, 
        tmpRxd => tmpRxd);

    etat : EltEtat 
    port map(
        reset => reset, 
        clk => clk, 
        tmpClk => tmpClk, 
        tmpRxd => tmpRxd, 
        read => read, 
        FErr => FErr, 
        OErr => OErr, 
        DRdy => DRdy,
        data => data);


end Behavioral;

UART_Emission/RxTester.vhd
--------------------------------------------------------------------------------
-- Company: 
-- Engineer:
--
-- Create Date:   14:05:45 01/19/2024
-- Design Name:   
-- Module Name:   /home/gaut/.Xilinx/UartTest/RxTester.vhd
-- Project Name:  UartTest
-- Target Device:  
-- Tool versions:  
-- Description:   
-- 
-- VHDL Test Bench Created by ISE for module: RxUnit
-- 
-- Dependencies:
-- 
-- Revision:
-- Revision 0.01 - File Created
-- Additional Comments:
--
-- Notes: 
-- This testbench has been automatically generated using types std_logic and
-- std_logic_vector for the ports of the unit under test.  Xilinx recommends
-- that these types always be used for the top-level I/O of a design in order
-- to guarantee that the testbench will bind correctly to the post-implementation 
-- simulation model.
--------------------------------------------------------------------------------
LIBRARY ieee;
USE ieee.std_logic_1164.ALL;
 
-- Uncomment the following library declaration if using
-- arithmetic functions with Signed or Unsigned values
--USE ieee.numeric_std.ALL;
 
ENTITY RxTester IS
END RxTester;
 
ARCHITECTURE behavior OF RxTester IS 
 
    -- Component Declaration for the Unit Under Test (UUT)
 
    COMPONENT RxUnit
    PORT(
         clk : IN  std_logic;
         reset : IN  std_logic;
         enable : IN  std_logic;
         read : IN  std_logic;
         rxd : IN  std_logic;
         data : OUT  std_logic_vector(7 downto 0);
         FErr : OUT  std_logic;
         OErr : OUT  std_logic;
         DRdy : OUT  std_logic
        );
    END COMPONENT;

   
   component clkUnit
    port (
      clk, reset : in std_logic;
      enableTX   : out std_logic;
      enableRX   : out std_logic
    );
  end component;
    
   -- clocks
   signal enableTX : std_logic;
   signal enableRX : std_logic;

   --Inputs
   signal clk : std_logic := '0';
   signal reset : std_logic := '0';
   signal enable : std_logic := '0';
	-- On supposera qu'on lis toujours correctement 
   signal read : std_logic := '1';
   signal rxd : std_logic := '0';

 	--Outputs
   signal data : std_logic_vector(7 downto 0);
   signal FErr : std_logic;
   signal OErr : std_logic;
   signal DRdy : std_logic;

   -- Clock period definitions
   constant clk_period : time := 10 ns;
 
BEGIN
 
	-- Instantiate the Unit Under Test (UUT)
   uut: RxUnit PORT MAP (
          clk => clk,
          reset => reset,
          enable => enableRx,
          read => read,
          rxd => rxd,
          data => data,
          FErr => FErr,
          OErr => OErr,
          DRdy => DRdy
        );


   clkUnit_inst : clkUnit
  port map(
    clk      => clk,
    reset    => reset,
    enableTX => enableTX,
    enableRX => enableRX
  );

   -- Clock process definitions
   clk_process :process
   begin
		clk <= '0';
		wait for clk_period/2;
		clk <= '1';
		wait for clk_period/2;
   end process;
 

   -- Stimulus process
   stim_proc: process
   variable data : std_logic_vector(7 downto 0);

   begin		
		
	
      -- hold reset state for 100 ns.
      wait for 100 ns;	

      reset <= '1';

      ----- Premier test ----------

      -- Idle 
      rxd <= '1';
      wait until enableTX = '1';

      -- Start bit
      rxd <= '0';
      wait until enableTX = '0';

      -- Data
      data := "10111101";
      for i in 7 downto 0 loop
         wait until enableTX = '1';
        rxd <= data(i);
        wait until enableTX = '0';
      end loop;
      wait until enableTX = '1';

      -- Stop bit
      rxd <= '1';
      wait until enableTX = '0';

      ----- Deuxieme test ----------

      wait for clk_period*10;

      -- Idle

      rxd <= '1';
      wait until enableTX = '1';

      -- Start bit

      rxd <= '0';
      wait until enableTX = '0';

      -- Data

      data := "11101111";
      for i in 0 to 7 loop
         wait until enableTX = '1';
        rxd <= data(i);
        wait until enableTX = '0';
      end loop;

      wait until enableTX = '1';

      -- Stop bit

      rxd <= '1';
      wait until enableTX = '0';

      -- insert stimulus here 

      wait;
   end process;

END;

UART_Emission/output.vcd
$date
   Fri Jan 19 17:18:03 2024
$end
$version
  P.20131013
$end
$timescale
  1ps
$end
$scope module rxtester $end
$var wire 1 l enabletx $end
$var wire 1 i enablerx $end
$var wire 1 j clk $end
$var wire 1 k reset $end
$var wire 1 % enable $end
$var wire 1 Q read $end
$var wire 1 H rxd $end
$var wire 1 \ data [7] $end
$var wire 1 [ data [6] $end
$var wire 1 Z data [5] $end
$var wire 1 Y data [4] $end
$var wire 1 X data [3] $end
$var wire 1 W data [2] $end
$var wire 1 V data [1] $end
$var wire 1 U data [0] $end
$var wire 1 R ferr $end
$var wire 1 S oerr $end
$var wire 1 T drdy $end
$scope module uut $end
$var wire 1 j clk $end
$var wire 1 k reset $end
$var wire 1 i enable $end
$var wire 1 Q read $end
$var wire 1 H rxd $end
$var wire 1 \ data [7] $end
$var wire 1 [ data [6] $end
$var wire 1 Z data [5] $end
$var wire 1 Y data [4] $end
$var wire 1 X data [3] $end
$var wire 1 W data [2] $end
$var wire 1 V data [1] $end
$var wire 1 U data [0] $end
$var wire 1 R ferr $end
$var wire 1 S oerr $end
$var wire 1 T drdy $end
$var wire 1 O tmpclk $end
$var wire 1 P tmprxd $end
$var wire 1 E drdy_bis $end
$scope module instants $end
$var wire 1 i enable $end
$var wire 1 k reset $end
$var wire 1 H rxd $end
$var wire 1 O tmpclk $end
$var wire 1 P tmprxd $end
$var wire 1 K savetmpclk $end
$upscope $end
$scope module etat $end
$var wire 1 k reset $end
$var wire 1 j clk $end
$var wire 1 O tmpclk $end
$var wire 1 P tmprxd $end
$var wire 1 Q read $end
$var wire 1 R ferr $end
$var wire 1 S oerr $end
$var wire 1 T drdy $end
$var wire 1 \ data [7] $end
$var wire 1 [ data [6] $end
$var wire 1 Z data [5] $end
$var wire 1 Y data [4] $end
$var wire 1 X data [3] $end
$var wire 1 W data [2] $end
$var wire 1 V data [1] $end
$var wire 1 U data [0] $end
$var wire 1 e savedata [7] $end
$var wire 1 d savedata [6] $end
$var wire 1 c savedata [5] $end
$var wire 1 b savedata [4] $end
$var wire 1 a savedata [3] $end
$var wire 1 ` savedata [2] $end
$var wire 1 _ savedata [1] $end
$var wire 1 ^ savedata [0] $end
$upscope $end
$upscope $end
$scope module clkUnit_inst $end
$var wire 1 j clk $end
$var wire 1 k reset $end
$var wire 1 l enabletx $end
$var wire 1 i enablerx $end
$scope module inst_div $end
$var wire 1 j clk $end
$var wire 1 k reset $end
$var wire 1 l nclk $end
$var wire 1 m top $end
$upscope $end
$upscope $end
$upscope $end
$enddefinitions $end
#0
$dumpvars
0l
0i
0j
0k
0%
1Q
0H
0\
0[
0Z
0Y
0X
0W
0V
0U
0R
0S
0T
xO
xP
xE
xK
xe
xd
xc
xb
xa
x`
x_
x^
0m
$end
#5000
1i
1j
#10000
0i
0j
#15000
1i
1j
#20000
0i
0j
#25000
1i
1j
#30000
0i
0j
#35000
1i
1j
#40000
0i
0j
#45000
1i
1j
#50000
0i
0j
#55000
1i
1j
#60000
0i
0j
#65000
1i
1j
#70000
0i
0j
#75000
1i
1j
#80000
0i
0j
#85000
1i
1j
#90000
0i
0j
#95000
1i
1j
#100000
0i
0j
1k
1H
#105000
1i
1j
0O
0K
#110000
0i
0j
#115000
1i
1j
#120000
0i
0j
#125000
1i
1j
#130000
0i
0j
#135000
1i
1j
#140000
0i
0j
#145000
1i
1j
#150000
0i
0j
#155000
1i
1j
#160000
0i
0j
#165000
1i
1j
#170000
0i
0j
#175000
1i
1j
#180000
0i
0j
#185000
1i
1j
#190000
0i
0j
#195000
1i
1j
#200000
0i
0j
#205000
1i
1j
#210000
0i
0j
#215000
1i
1j
#220000
0i
0j
#225000
1i
1j
#230000
0i
0j
#235000
1i
1j
#240000
0i
0j
#245000
1i
1j
#250000
0i
0j
#255000
1l
1i
1j
0H
#260000
0i
0j
#265000
0l
1i
1j
#270000
0i
0j
#275000
1i
1j
#280000
0i
0j
#285000
1i
1j
#290000
0i
0j
#295000
1i
1j
#300000
0i
0j
#305000
1i
1j
#310000
0i
0j
#315000
1i
1j
#320000
0i
0j
#325000
1i
1j
#330000
0i
0j
#335000
1i
1j
#340000
0i
0j
#345000
1i
1j
1O
0P
1K
#350000
0i
0j
#355000
1i
1j
0O
#360000
0i
0j
#365000
1i
1j
#370000
0i
0j
#375000
1i
1j
#380000
0i
0j
#385000
1i
1j
#390000
0i
0j
#395000
1i
1j
#400000
0i
0j
#405000
1i
1j
#410000
0i
0j
#415000
1l
1i
1j
1H
#420000
0i
0j
#425000
0l
1i
1j
#430000
0i
0j
#435000
1i
1j
#440000
0i
0j
#445000
1i
1j
#450000
0i
0j
#455000
1i
1j
#460000
0i
0j
#465000
1i
1j
#470000
0i
0j
#475000
1i
1j
#480000
0i
0j
#485000
1i
1j
#490000
0i
0j
#495000
1i
1j
#500000
0i
0j
#505000
1i
1j
1O
1P
#510000
0i
0j
#515000
1i
1j
0O
1e
#520000
0i
0j
#525000
1i
1j
#530000
0i
0j
#535000
1i
1j
#540000
0i
0j
#545000
1i
1j
#550000
0i
0j
#555000
1i
1j
#560000
0i
0j
#565000
1i
1j
#570000
0i
0j
#575000
1l
1i
1j
0H
#580000
0i
0j
#585000
0l
1i
1j
#590000
0i
0j
#595000
1i
1j
#600000
0i
0j
#605000
1i
1j
#610000
0i
0j
#615000
1i
1j
#620000
0i
0j
#625000
1i
1j
#630000
0i
0j
#635000
1i
1j
#640000
0i
0j
#645000
1i
1j
#650000
0i
0j
#655000
1i
1j
#660000
0i
0j
#665000
1i
1j
1O
0P
#670000
0i
0j
#675000
1i
1j
0O
0d
#680000
0i
0j
#685000
1i
1j
#690000
0i
0j
#695000
1i
1j
#700000
0i
0j
#705000
1i
1j
#710000
0i
0j
#715000
1i
1j
#720000
0i
0j
#725000
1i
1j
#730000
0i
0j
#735000
1l
1i
1j
1H
#740000
0i
0j
#745000
0l
1i
1j
#750000
0i
0j
#755000
1i
1j
#760000
0i
0j
#765000
1i
1j
#770000
0i
0j
#775000
1i
1j
#780000
0i
0j
#785000
1i
1j
#790000
0i
0j
#795000
1i
1j
#800000
0i
0j
#805000
1i
1j
#810000
0i
0j
#815000
1i
1j
#820000
0i
0j
#825000
1i
1j
1O
1P
#830000
0i
0j
#835000
1i
1j
0O
1c
#840000
0i
0j
#845000
1i
1j
#850000
0i
0j
#855000
1i
1j
#860000
0i
0j
#865000
1i
1j
#870000
0i
0j
#875000
1i
1j
#880000
0i
0j
#885000
1i
1j
#890000
0i
0j
#895000
1l
1i
1j
#900000
0i
0j
#905000
0l
1i
1j
#910000
0i
0j
#915000
1i
1j
#920000
0i
0j
#925000
1i
1j
#930000
0i
0j
#935000
1i
1j
#940000
0i
0j
#945000
1i
1j
#950000
0i
0j
#955000
1i
1j
#960000
0i
0j
#965000
1i
1j
#970000
0i
0j
#975000
1i
1j
#980000
0i
0j
#985000
1i
1j
1O
#990000
0i
0j
#995000
1i
1j
0O
1b
#1000000
0i
0j
#1005000
1i
1j
#1010000
0i
0j
#1015000
1i
1j
#1020000
0i
0j
#1025000
1i
1j
#1030000
0i
0j
#1035000
1i
1j
#1040000
0i
0j
#1045000
1i
1j
#1050000
0i
0j
#1055000
1l
1i
1j
#1060000
0i
0j
#1065000
0l
1i
1j
#1070000
0i
0j
#1075000
1i
1j
#1080000
0i
0j
#1085000
1i
1j
#1090000
0i
0j
#1095000
1i
1j
#1100000
0i
0j
#1105000
1i
1j
#1110000
0i
0j
#1115000
1i
1j
#1120000
0i
0j
#1125000
1i
1j
#1130000
0i
0j
#1135000
1i
1j
#1140000
0i
0j
#1145000
1i
1j
1O
#1150000
0i
0j
#1155000
1i
1j
0O
1a
#1160000
0i
0j
#1165000
1i
1j
#1170000
0i
0j
#1175000
1i
1j
#1180000
0i
0j
#1185000
1i
1j
#1190000
0i
0j
#1195000
1i
1j
#1200000
0i
0j
#1205000
1i
1j
#1210000
0i
0j
#1215000
1l
1i
1j
#1220000
0i
0j
#1225000
0l
1i
1j
#1230000
0i
0j
#1235000
1i
1j
#1240000
0i
0j
#1245000
1i
1j
#1250000
0i
0j
#1255000
1i
1j
#1260000
0i
0j
#1265000
1i
1j
#1270000
0i
0j
#1275000
1i
1j
#1280000
0i
0j
#1285000
1i
1j
#1290000
0i
0j
#1295000
1i
1j
#1300000
0i
0j
#1305000
1i
1j
1O
#1310000
0i
0j
#1315000
1i
1j
0O
1`
#1320000
0i
0j
#1325000
1i
1j
#1330000
0i
0j
#1335000
1i
1j
#1340000
0i
0j
#1345000
1i
1j
#1350000
0i
0j
#1355000
1i
1j
#1360000
0i
0j
#1365000
1i
1j
#1370000
0i
0j
#1375000
1l
1i
1j
0H
#1380000
0i
0j
#1385000
0l
1i
1j
#1390000
0i
0j
#1395000
1i
1j
#1400000
0i
0j
#1405000
1i
1j
#1410000
0i
0j
#1415000
1i
1j
#1420000
0i
0j
#1425000
1i
1j
#1430000
0i
0j
#1435000
1i
1j
#1440000
0i
0j
#1445000
1i
1j
#1450000
0i
0j
#1455000
1i
1j
#1460000
0i
0j
#1465000
1i
1j
1O
0P
#1470000
0i
0j
#1475000
1i
1j
0O
0_
#1480000
0i
0j
#1485000
1i
1j
#1490000
0i
0j
#1495000
1i
1j
#1500000
0i
0j
#1505000
1i
1j
#1510000
0i
0j
#1515000
1i
1j
#1520000
0i
0j
#1525000
1i
1j
#1530000
0i
0j
#1535000
1l
1i
1j
1H
#1540000
0i
0j
#1545000
0l
1i
1j
#1550000
0i
0j
#1555000
1i
1j
#1560000
0i
0j
#1565000
1i
1j
#1570000
0i
0j
#1575000
1i
1j
#1580000
0i
0j
#1585000
1i
1j
#1590000
0i
0j
#1595000
1i
1j
#1600000
0i
0j
#1605000
1i
1j
#1610000
0i
0j
#1615000
1i
1j
#1620000
0i
0j
#1625000
1i
1j
1O
1P
#1630000
0i
0j
#1635000
1i
1j
0O
1^
#1640000
0i
0j
#1645000
1i
1j
#1650000
0i
0j
#1655000
1i
1j
#1660000
0i
0j
#1665000
1i
1j
#1670000
0i
0j
#1675000
1i
1j
#1680000
0i
0j
#1685000
1i
1j
#1690000
0i
0j
#1695000
1l
1i
1j
#1700000
0i
0j
#1705000
0l
1i
1j
#1710000
0i
0j
#1715000
1i
1j
#1720000
0i
0j
#1725000
1i
1j
#1730000
0i
0j
#1735000
1i
1j
#1740000
0i
0j
#1745000
1i
1j
#1750000
0i
0j
#1755000
1i
1j
#1760000
0i
0j
#1765000
1i
1j
#1770000
0i
0j
#1775000
1i
1j
#1780000
0i
0j
#1785000
1i
1j
1O
#1790000
0i
0j
#1795000
1i
1j
1\
1Z
1Y
1X
1W
1U
1T
0O
0K
#1800000
0i
0j
#1805000
1i
1j
#1810000
0i
0j
#1815000
1i
1j
#1820000
0i
0j
#1825000
1i
1j
0T
#1830000
0i
0j
#1835000
1i
1j
#1840000
0i
0j
#1845000
1i
1j
#1850000
0i
0j
#1855000
1l
1i
1j
0H
#1860000
0i
0j
#1865000
0l
1i
1j
#1870000
0i
0j
#1875000
1i
1j
#1880000
0i
0j
#1885000
1i
1j
#1890000
0i
0j
#1895000
1i
1j
#1900000
0i
0j
#1905000
1i
1j
#1910000
0i
0j
#1915000
1i
1j
#1920000
0i
0j
#1925000
1i
1j
#1930000
0i
0j
#1935000
1i
1j
#1940000
0i
0j
#1945000
1i
1j
1O
0P
1K
#1950000
0i
0j
#1955000
1i
1j
0O
xe
xd
xc
xb
xa
x`
x_
x^
#1960000
0i
0j
#1965000
1i
1j
#1970000
0i
0j
#1975000
1i
1j
#1980000
0i
0j
#1985000
1i
1j
#1990000
0i
0j
#1995000
1i
1j
#2000000
0i
0j
#2005000
1i
1j
#2010000
0i
0j
#2015000
1l
1i
1j
1H
#2020000
0i
0j
#2025000
0l
1i
1j
#2030000
0i
0j
#2035000
1i
1j
#2040000
0i
0j
#2045000
1i
1j
#2050000
0i
0j
#2055000
1i
1j
#2060000
0i
0j
#2065000
1i
1j
#2070000
0i
0j
#2075000
1i
1j
#2080000
0i
0j
#2085000
1i
1j
#2090000
0i
0j
#2095000
1i
1j
#2100000
0i
0j
#2105000
1i
1j
1O
1P
#2110000
0i
0j
#2115000
1i
1j
0O
1e
#2120000
0i
0j
#2125000
1i
1j
#2130000
0i
0j
#2135000
1i
1j
#2140000
0i
0j
#2145000
1i
1j
#2150000
0i
0j
#2155000
1i
1j
#2160000
0i
0j
#2165000
1i
1j
#2170000
0i
0j
#2175000
1l
1i
1j
#2180000
0i
0j
#2185000
0l
1i
1j
#2190000
0i
0j
#2195000
1i
1j
#2200000
0i
0j
#2205000
1i
1j
#2210000
0i
0j
#2215000
1i
1j
#2220000
0i
0j
#2225000
1i
1j
#2230000
0i
0j
#2235000
1i
1j
#2240000
0i
0j
#2245000
1i
1j
#2250000
0i
0j
#2255000
1i
1j
#2260000
0i
0j
#2265000
1i
1j
1O
#2270000
0i
0j
#2275000
1i
1j
0O
1d
#2280000
0i
0j
#2285000
1i
1j
#2290000
0i
0j
#2295000
1i
1j
#2300000
0i
0j
#2305000
1i
1j
#2310000
0i
0j
#2315000
1i
1j
#2320000
0i
0j
#2325000
1i
1j
#2330000
0i
0j
#2335000
1l
1i
1j
#2340000
0i
0j
#2345000
0l
1i
1j
#2350000
0i
0j
#2355000
1i
1j
#2360000
0i
0j
#2365000
1i
1j
#2370000
0i
0j
#2375000
1i
1j
#2380000
0i
0j
#2385000
1i
1j
#2390000
0i
0j
#2395000
1i
1j
#2400000
0i
0j
#2405000
1i
1j
#2410000
0i
0j
#2415000
1i
1j
#2420000
0i
0j
#2425000
1i
1j
1O
#2430000
0i
0j
#2435000
1i
1j
0O
1c
#2440000
0i
0j
#2445000
1i
1j
#2450000
0i
0j
#2455000
1i
1j
#2460000
0i
0j
#2465000
1i
1j
#2470000
0i
0j
#2475000
1i
1j
#2480000
0i
0j
#2485000
1i
1j
#2490000
0i
0j
#2495000
1l
1i
1j
#2500000
0i
0j
#2505000
0l
1i
1j
#2510000
0i
0j
#2515000
1i
1j
#2520000
0i
0j
#2525000
1i
1j
#2530000
0i
0j
#2535000
1i
1j
#2540000
0i
0j
#2545000
1i
1j
#2550000
0i
0j
#2555000
1i
1j
#2560000
0i
0j
#2565000
1i
1j
#2570000
0i
0j
#2575000
1i
1j
#2580000
0i
0j
#2585000
1i
1j
1O
#2590000
0i
0j
#2595000
1i
1j
0O
1b
#2600000
0i
0j
#2605000
1i
1j
#2610000
0i
0j
#2615000
1i
1j
#2620000
0i
0j
#2625000
1i
1j
#2630000
0i
0j
#2635000
1i
1j
#2640000
0i
0j
#2645000
1i
1j
#2650000
0i
0j
#2655000
1l
1i
1j
0H
#2660000
0i
0j
#2665000
0l
1i
1j
#2670000
0i
0j
#2675000
1i
1j
#2680000
0i
0j
#2685000
1i
1j
#2690000
0i
0j
#2695000
1i
1j
#2700000
0i
0j
#2705000
1i
1j
#2710000
0i
0j
#2715000
1i
1j
#2720000
0i
0j
#2725000
1i
1j
#2730000
0i
0j
#2735000
1i
1j
#2740000
0i
0j
#2745000
1i
1j
1O
0P
#2750000
0i
0j
#2755000
1i
1j
0O
0a
#2760000
0i
0j
#2765000
1i
1j
#2770000
0i
0j
#2775000
1i
1j
#2780000
0i
0j
#2785000
1i
1j
#2790000
0i
0j
#2795000
1i
1j
#2800000
0i
0j
#2805000
1i
1j
#2810000
0i
0j
#2815000
1l
1i
1j
1H
#2820000
0i
0j
#2825000
0l
1i
1j
#2830000
0i
0j
#2835000
1i
1j
#2840000
0i
0j
#2845000
1i
1j
#2850000
0i
0j
#2855000
1i
1j
#2860000
0i
0j
#2865000
1i
1j
#2870000
0i
0j
#2875000
1i
1j
#2880000
0i
0j
#2885000
1i
1j
#2890000
0i
0j
#2895000
1i
1j
#2900000
0i
0j
#2905000
1i
1j
1O
1P
#2910000
0i
0j
#2915000
1i
1j
0O
1`
#2920000
0i
0j
#2925000
1i
1j
#2930000
0i
0j
#2935000
1i
1j
#2940000
0i
0j
#2945000
1i
1j
#2950000
0i
0j
#2955000
1i
1j
#2960000
0i
0j
#2965000
1i
1j
#2970000
0i
0j
#2975000
1l
1i
1j
#2980000
0i
0j
#2985000
0l
1i
1j
#2990000
0i
0j
#2995000
1i
1j
#3000000
0i
0j
#3005000
1i
1j
#3010000
0i
0j
#3015000
1i
1j
#3020000
0i
0j
#3025000
1i
1j
#3030000
0i
0j
#3035000
1i
1j
#3040000
0i
0j
#3045000
1i
1j
#3050000
0i
0j
#3055000
1i
1j
#3060000
0i
0j
#3065000
1i
1j
1O
#3070000
0i
0j
#3075000
1i
1j
0O
1_
#3080000
0i
0j
#3085000
1i
1j
#3090000
0i
0j
#3095000
1i
1j
#3100000
0i
0j
#3105000
1i
1j
#3110000
0i
0j
#3115000
1i
1j
#3120000
0i
0j
#3125000
1i
1j
#3130000
0i
0j
#3135000
1l
1i
1j
#3140000
0i
0j
#3145000
0l
1i
1j
#3150000
0i
0j
#3155000
1i
1j
#3160000
0i
0j
#3165000
1i
1j
#3170000
0i
0j
#3175000
1i
1j
#3180000
0i
0j
#3185000
1i
1j
#3190000
0i
0j
#3195000
1i
1j
#3200000
0i
0j
#3205000
1i
1j
#3210000
0i
0j
#3215000
1i
1j
#3220000
0i
0j
